{"issue":"i26p5","source":"homecoming","extract_date":"2020-08-11T21:28:16.811569100-07:00","name":"Mastermind_Pets.Dire_Wolf_3","display_name":"Dire Wolf","display_help":"Beasts","icon":"https://reborn-team.github.io/PowersAPI/assets/powers/db/beastmastery_petterriblehowl.png","show_in_inventory":"Show","show_in_power_management":true,"show_in_power_info":true,"ordered_power_names":["Mastermind_Pets.Dire_Wolf_3.Terrible_Howl","Mastermind_Pets.Dire_Wolf_3.PM_Terrible_Howl","Mastermind_Pets.Dire_Wolf_3.Will_of_the_Wild","Mastermind_Pets.Dire_Wolf_3.Tame_Beasts"],"powers":[{"name":"Mastermind_Pets.Dire_Wolf_3.Terrible_Howl","display_name":"Terrible Howl","icon":"https://reborn-team.github.io/PowersAPI/assets/powers/db/beastmastery_petterriblehowl.png","display_help":"The Dire Wolf is capable of letting out a Terrible Roar that will cause High Cold damage, slow and terrorize all nearby foes for a short time. Recharge: Slow","display_short_help":"PBAoE, High DMG(Cold), Foe Terrorize, Minor DoT(Cold), -Rech, -Speed","display_info":{"Effect Area":"AoE — 15 ft. radius (16 targets max)","Recharge Time":"1m 0s","Endurance Cost":"16.64","Power Type":"Click","Activation Time":"3.67s","Target Type":"Self","Attack Types":"Melee, Cold","Available Level":"1"},"attack_types":["Melee_Def","Cold_Def"],"enhancements_allowed":["Reduce Endurance Cost","Enhance Fear"],"available_at_level":1,"auto_issue":false,"power_type":"Click","accuracy":1.0,"effect_area":{"area":"AoE","max_targets_hit":16,"radius_feet":15.0},"target_type_tags":["Self","Alive","Dead"],"display_target_type":"Self","requires_line_of_sight":true,"modes_disallowed":["Disable_All"],"activate":{"cast_time":3.67,"animation_time":3.67,"animation_time_before_hit":1.0,"recharge_time":60.0,"endurance_cost":16.64},"effect_groups":[{"pve_or_pvp":"PVE","visible_in_info_window":true,"chance_percent":100.0,"requires":["target>enttype == critter"],"effects":[{"attributes":["Terrorized"],"applies_to":"CurrentModifier","application_type":"OnTick","target_type":"Affected","magnitude":3.0,"duration":"InSecondsScaled","flags":["ResistDuration","CombatModDuration"],"stacking":{"behavior":"Stack","by_caster":true},"scaled":[{"archetype":"Mastermind","duration_seconds":11.92,"display_info":["3.0 terrorize for 11.92s on target"],"base_value":1.49,"scale":8.0}]}]},{"pve_or_pvp":"PVP","visible_in_info_window":true,"chance_percent":100.0,"requires":["target>enttype == player"],"effects":[{"attributes":["Terrorized"],"applies_to":"CurrentModifier","application_type":"OnTick","target_type":"Affected","magnitude":3.0,"duration":"InSecondsScaled","flags":["ResistDuration","CombatModDuration"],"stacking":{"behavior":"Stack","by_caster":true},"scaled":[{"archetype":"Mastermind","duration_seconds":2.0,"display_info":["3.0 terrorize for 2s on target"],"base_value":2.0,"scale":1.0}]}]},{"visible_in_info_window":true,"chance_percent":100.0,"effects":[{"attributes":["Cold_Dmg"],"applies_to":"AbsoluteValue","application_type":"Immediate","target_type":"Affected","magnitude":1.0,"duration":"Instant","flags":["ResistMagnitude","CombatModMagnitude"],"stacking":{"behavior":"Stack","by_caster":true},"scaled":[{"archetype":"Mastermind","damage":45.88,"average":45.88,"per_activation":12.5,"per_cast_cycle":0.72,"display_info":["45.88 cold damage on target"],"base_value":-30.5856,"scale":1.5}]},{"attributes":["Cold_Dmg"],"applies_to":"AbsoluteValue","application_type":"OnTick","tick_chance_percent":100.0,"target_type":"Affected","magnitude":1.0,"duration":"InSeconds","duration_seconds":2.1,"after_delay_seconds":0.5,"continuous_apply_seconds":1.0,"ticks":3,"flags":["ResistMagnitude","CombatModMagnitude"],"stacking":{"behavior":"Stack","by_caster":true},"scaled":[{"archetype":"Mastermind","damage":6.12,"average":6.12,"per_activation":1.67,"per_cast_cycle":0.1,"display_info":["3 ticks of 6.12 cold damage over 2.1s on target after 0.5s delay"],"base_value":-30.5856,"scale":0.2}]},{"attributes":["JumpHeight","RechargeTime"],"applies_to":"Strength","application_type":"OnTick","tick_chance_percent":100.0,"target_type":"Affected","magnitude":1.0,"duration":"InSeconds","duration_seconds":15.0,"flags":["IgnoreStrength","ResistMagnitude","CombatModMagnitude"],"stacking":{"behavior":"Stack","by_caster":true},"scaled":[{"archetype":"Mastermind","percent":-30.0,"display_info":["-30.00% strength to jump height, recharge for 15s on target","Ignores buffs and enhancements"],"base_value":-1.0,"scale":0.3}]},{"attributes":["RunningSpeed","FlyingSpeed","JumpingSpeed"],"applies_to":"CurrentValue","application_type":"OnTick","tick_chance_percent":100.0,"target_type":"Affected","magnitude":1.0,"duration":"InSeconds","duration_seconds":15.0,"flags":["ResistMagnitude","CombatModMagnitude"],"stacking":{"behavior":"Stack","by_caster":true},"scaled":[{"archetype":"Mastermind","percent":-30.0,"display_info":["-30.00% run speed, fly speed, jump speed for 15s on target"],"base_value":-1.0,"scale":0.3}]},{"attributes":["Fly"],"applies_to":"CurrentValue","application_type":"OnTick","tick_chance_percent":100.0,"target_type":"Affected","duration":"InSeconds","duration_seconds":15.0,"flags":["ResistMagnitude","CombatModMagnitude"],"stacking":{"behavior":"Stack","by_caster":true},"scaled":[{"archetype":"Mastermind","magnitude":-1.6,"display_info":["-1.6 fly protection for 15s on target"],"base_value":1.0,"scale":-1.6}]}]},{"visible_in_info_window":true,"chance_percent":0.0,"effects":[{"attributes":["Lethal_Dmg"],"applies_to":"AbsoluteValue","application_type":"Immediate","target_type":"Affected","magnitude":1.0,"duration":"Instant","flags":["ResistMagnitude","CombatModMagnitude"],"stacking":{"behavior":"Stack","by_caster":true},"scaled":[{"archetype":"Mastermind","damage":22.94,"display_info":["22.94 lethal damage on target"],"base_value":-30.5856,"scale":0.75}]}]}]},{"name":"Mastermind_Pets.Dire_Wolf_3.PM_Terrible_Howl","display_name":"Pack Mentality Granter","icon":"https://reborn-team.github.io/PowersAPI/assets/powers/db/beastmastery_petterriblehowl.png","display_help":"This power has a chance to grant a charge of Pack Mentality.","display_short_help":"Grants Pack Mentality","display_info":{"Target Type":"Self","Power Type":"Click","Effect Area":"AoE — 30 ft. radius (1 targets max)","Available Level":"1"},"available_at_level":1,"auto_issue":false,"power_type":"Click","accuracy":1.0,"effect_area":{"area":"AoE","max_targets_hit":1,"radius_feet":30.0},"target_type_tags":["Self","Alive","Dead"],"display_target_type":"Self","target_auto_hit_tags":[["Root_Owner"]],"requires_line_of_sight":true,"modes_disallowed":["Disable_All"],"activate":{"cast_time":0.0,"animation_time":1.17,"animation_time_before_hit":0.5,"recharge_time":0.0,"endurance_cost":0.0},"effect_groups":[{"visible_in_info_window":true,"chance_percent":100.0,"requires":["!target.ownPower?(temporary_powers.temporary_powers.Pack_Mentality_Lock)"],"effects":[{"attributes":["Grant Power"],"applies_to":"Special","application_type":"Immediate","target_type":"Affected","duration":"Instant","flags":["IgnoreStrength","IgnoreResistance","CombatModMagnitude"],"parameter":{"power":{"powers":[{"name":"Temporary_Powers.Temporary_Powers.Pack_Mentality","url":"https://reborn-team.github.io/PowersAPI/hc_homecoming/temporary-powers/temporary-powers/"}]}},"stacking":{"behavior":"Stack","by_caster":true}}]}]},{"name":"Mastermind_Pets.Dire_Wolf_3.Will_of_the_Wild","display_name":"Will of the Wild","icon":"https://reborn-team.github.io/PowersAPI/assets/powers/3c/beastmastery_petwillofthewild.png","display_help":"When the Dire Wolf is dangerously low on health it will become enraged and suffer significantly less damage for a short time as well as recovering a portion of its health. Once this power wears off it will leave it partially drained of endurance. Note that Will of the Wild is unaffected by Recharge Time changes. Recharge: Long","display_short_help":"Self, +Max HP, +Res(Lethal, Smash, Fire, Cold)","display_info":{"Target Type":"Self","Recharge Time":"2m 0s","Effect Area":"Single Target","Available Level":"1","Power Type":"Click","Activation Time":"1.6s","Endurance Cost":"13.00"},"enhancements_allowed":["Enhance Damage Resistance","Reduce Endurance Cost","Enhance Heal"],"available_at_level":1,"auto_issue":false,"power_type":"Click","accuracy":1.0,"effect_area":{"area":"SingleTarget"},"target_type_tags":["Self","Alive","Dead"],"display_target_type":"Self","target_auto_hit_tags":[["Self","Alive","Dead"]],"display_target_auto_hit":["Self"],"requires_line_of_sight":true,"modes_disallowed":["Disable_All"],"activate":{"cast_time":1.6,"animation_time":1.6,"animation_time_before_hit":0.23,"recharge_time":120.0,"endurance_cost":13.0},"effect_groups":[{"visible_in_info_window":true,"chance_percent":100.0,"effects":[{"attributes":["HitPoints"],"applies_to":"MaxValue","application_type":"OnTick","tick_chance_percent":100.0,"target_type":"Self","magnitude":1.0,"duration":"InSeconds","duration_seconds":45.0,"flags":["IgnoreStrength","IgnoreResistance","CombatModMagnitude"],"stacking":{"behavior":"Stack","by_caster":true},"scaled":[{"archetype":"Mastermind","healing":160.63,"display_info":["160.63 hit points for 45s on self","Ignores buffs and enhancements","Unresistable"],"base_value":80.3173,"scale":2.0}]},{"attributes":["HitPoints"],"applies_to":"MaxValue","application_type":"OnTick","tick_chance_percent":100.0,"target_type":"Self","magnitude":1.0,"duration":"InSeconds","duration_seconds":45.0,"flags":["IgnoreResistance","CombatModMagnitude"],"stacking":{"behavior":"Stack","by_caster":true},"scaled":[{"archetype":"Mastermind","healing":160.63,"display_info":["160.63 hit points for 45s on self","Unresistable"],"base_value":80.3173,"scale":2.0}]},{"attributes":["Healing_Dmg"],"applies_to":"AbsoluteValue","application_type":"Immediate","target_type":"Self","magnitude":1.0,"duration":"Instant","flags":["IgnoreResistance","CombatModMagnitude"],"stacking":{"behavior":"Stack","by_caster":true},"scaled":[{"archetype":"Mastermind","healing":321.27,"average":321.27,"per_activation":200.79,"per_cast_cycle":2.64,"display_info":["321.27 heal on self","Unresistable"],"base_value":80.3173,"scale":4.0}]},{"attributes":["Smashing_Dmg","Lethal_Dmg","Fire_Dmg","Cold_Dmg"],"applies_to":"Resistance","application_type":"OnTick","tick_chance_percent":100.0,"target_type":"Self","magnitude":1.0,"duration":"InSeconds","duration_seconds":45.0,"flags":["IgnoreStrength","IgnoreResistance","CombatModMagnitude"],"stacking":{"behavior":"Replace","by_caster":true},"scaled":[{"archetype":"Mastermind","percent":37.35,"display_info":["37.35% resistance to smashing damage, lethal damage, fire damage, cold damage for 45s on self","Ignores buffs and enhancements","Unresistable"],"base_value":2.49,"scale":0.15}]}]}]},{"name":"Mastermind_Pets.Dire_Wolf_3.Tame_Beasts","display_name":"Tame Beasts","icon":"https://reborn-team.github.io/PowersAPI/assets/powers/d8/beastmastery_tamebeasts.png","display_help":"Your Dire Wolf has been tamed it can now use Terrible Howl and Will of the Wild.","display_short_help":"Tame Beasts","display_info":{"Target Type":"Self","Effect Area":"Single Target","Available Level":"1","Power Type":"Auto"},"available_at_level":1,"auto_issue":false,"power_type":"Auto","accuracy":1.0,"effect_area":{"area":"SingleTarget"},"target_type_tags":["Self","Alive","Dead"],"display_target_type":"Self","target_auto_hit_tags":[["Self","Alive","Dead"]],"display_target_auto_hit":["Self"],"requires_line_of_sight":true,"activate":{"cast_time":0.0,"animation_time":1.17,"animation_time_before_hit":0.5,"recharge_time":0.0,"auto_cast_interval":10.0,"endurance_cost":0.0},"effect_groups":[{"visible_in_info_window":true,"chance_percent":100.0,"effects":[{"attributes":["Evade"],"applies_to":"CurrentValue","application_type":"OnTick","target_type":"Self","magnitude":10.0,"duration":"InSecondsScaled","flags":["IgnoreStrength","IgnoreResistance","CombatModDuration"],"stacking":{"behavior":"Replace","by_caster":true},"scaled":[{"archetype":"Mastermind","duration_seconds":10.25,"base_value":1.0,"scale":10.25}]}]}]}]}