{
  "issue": "i26p5",
  "source": "homecoming",
  "extract_date": "2020-08-11T21:52:57.192132400-07:00",
  "name": "Arachnos_Soldiers.Arachnos_Soldier",
  "display_name": "Arachnos Soldier",
  "display_help": "Character with Arachnos Soldier training begin their careers as Wolf Spiders. Wolf Spider characters have a strong mix of Melee and Ranged attacks and strong protective powers available via their power armor. Beginning at level 24, the player has to choose whether he will progress down the \"Crab Spider\" or \"Bane Spider\" path. Crab Spiders gain access to the \"backpack\" and the powerful claw/cone attacks it provides, while the Bane Spider track provides stealth and a stronger focus on melee.",
  "icon": "https://reborn-team.github.io/PowersAPI/assets/powers/4a/arachnossoldier_singleshot.png",
  "show_in_inventory": "Show",
  "show_in_power_management": true,
  "show_in_power_info": true,
  "ordered_power_names": [
    "Arachnos_Soldiers.Arachnos_Soldier.Single_Shot",
    "Arachnos_Soldiers.Arachnos_Soldier.Pummel",
    "Arachnos_Soldiers.Arachnos_Soldier.Burst",
    "Arachnos_Soldiers.Arachnos_Soldier.WS_Wide_Area_Web_Grenade",
    "Arachnos_Soldiers.Arachnos_Soldier.Heavy_Burst",
    "Arachnos_Soldiers.Arachnos_Soldier.Bayonet",
    "Arachnos_Soldiers.Arachnos_Soldier.Venom_Grenade",
    "Arachnos_Soldiers.Arachnos_Soldier.Frag_Grenade"
  ],
  "powers": [
    {
      "name": "Arachnos_Soldiers.Arachnos_Soldier.Single_Shot",
      "display_name": "Single Shot",
      "icon": "https://reborn-team.github.io/PowersAPI/assets/powers/4a/arachnossoldier_singleshot.png",
      "display_help": "A quick single shot from the Arachnos Sub-machinegun. Extremely accurate. Damage: Minor, Recharge: Fast",
      "display_short_help": "Ranged, Minor DMG(Lethal), Foe -DEF",
      "display_info": {
        "Target Type": "Enemies",
        "Recharge Time": "4s",
        "Effect Area": "Single Target",
        "Activation Time": "0.9s",
        "Power Range": "80 ft.",
        "Available Level": "1",
        "Attack Types": "Ranged, Lethal",
        "Power Type": "Click",
        "Endurance Cost": "5.20"
      },
      "attack_types": [
        "Ranged_Def",
        "Lethal_Def"
      ],
      "enhancements_allowed": [
        "Reduce Endurance Cost",
        "Enhance Range",
        "Enhance Recharge Speed",
        "Enhance Defense DeBuff",
        "Enhance Damage",
        "Enhance Accuracy"
      ],
      "enhancement_set_categories_allowed": [
        "Defense Debuff",
        "Ranged Damage",
        "Universal Damage Sets",
        "Soldiers of Arachnos Archetype Sets",
        "Accurate Defense Debuff"
      ],
      "available_at_level": 1,
      "auto_issue": false,
      "power_type": "Click",
      "accuracy": 1.05,
      "effect_area": {
        "area": "SingleTarget",
        "range_feet": 80.0
      },
      "target_type_tags": [
        "Foe"
      ],
      "display_target_type": "Enemies",
      "requires_line_of_sight": true,
      "modes_disallowed": [
        "Disable_All"
      ],
      "activate": {
        "cast_time": 0.9,
        "animation_time": 0.9,
        "animation_time_before_hit": 0.27,
        "recharge_time": 4.0,
        "endurance_cost": 5.2
      },
      "effect_groups": [
        {
          "pve_or_pvp": "PVE",
          "visible_in_info_window": true,
          "chance_percent": 100.0,
          "requires": [
            "target>enttype == critter"
          ],
          "effects": [
            {
              "attributes": [
                "Lethal_Dmg"
              ],
              "applies_to": "AbsoluteValue",
              "application_type": "Immediate",
              "target_type": "Affected",
              "magnitude": 1.0,
              "duration": "Instant",
              "flags": [
                "ResistMagnitude",
                "CombatModMagnitude"
              ],
              "stacking": {
                "behavior": "Stack",
                "by_caster": true
              },
              "scaled": [
                {
                  "archetype": "Arachnos Soldier",
                  "damage": 55.61,
                  "average": 55.61,
                  "per_activation": 61.79,
                  "per_cast_cycle": 11.35,
                  "display_info": [
                    "55.61 lethal damage on target"
                  ],
                  "base_value": -55.6102,
                  "scale": 1.0
                }
              ]
            }
          ]
        },
        {
          "visible_in_info_window": true,
          "chance_percent": 100.0,
          "effects": [
            {
              "attributes": [
                "Defense"
              ],
              "applies_to": "CurrentValue",
              "application_type": "OnTick",
              "tick_chance_percent": 100.0,
              "target_type": "Affected",
              "magnitude": 1.0,
              "duration": "InSeconds",
              "duration_seconds": 5.0,
              "flags": [
                "ResistMagnitude",
                "CombatModMagnitude"
              ],
              "stacking": {
                "behavior": "Stack",
                "by_caster": true
              },
              "scaled": [
                {
                  "archetype": "Arachnos Soldier",
                  "percent": -7.5,
                  "display_info": [
                    "-7.50% strength to defense for 5s on target"
                  ],
                  "base_value": -0.075,
                  "scale": 1.0
                }
              ]
            }
          ]
        },
        {
          "pve_or_pvp": "PVP",
          "visible_in_info_window": true,
          "chance_percent": 100.0,
          "requires": [
            "target>enttype == player"
          ],
          "effects": [
            {
              "attributes": [
                "Lethal_Dmg"
              ],
              "applies_to": "AbsoluteValue",
              "application_type": "Immediate",
              "target_type": "Affected",
              "magnitude": 1.0,
              "duration": "Instant",
              "flags": [
                "ResistMagnitude",
                "CombatModMagnitude"
              ],
              "stacking": {
                "behavior": "Stack",
                "by_caster": true
              },
              "scaled": [
                {
                  "archetype": "Arachnos Soldier",
                  "damage": 67.13,
                  "average": 67.13,
                  "per_activation": 74.59,
                  "per_cast_cycle": 13.7,
                  "display_info": [
                    "67.13 lethal damage on target"
                  ],
                  "base_value": -56.4132,
                  "scale": 1.1899
                }
              ]
            }
          ]
        }
      ]
    },
    {
      "name": "Arachnos_Soldiers.Arachnos_Soldier.Pummel",
      "display_name": "Pummel",
      "icon": "https://reborn-team.github.io/PowersAPI/assets/powers/40/arachnossoldier_pummel.png",
      "display_help": "You can smash your opponents in close combat with the butt of your sub-machine gun to deal minor smashing damage. Pummel has a high chance to disorient your foe for a brief time. NOTE: This power will deal critical damage if used after a successful Placate or while the user is hidden with the Bane Spider Cloaking Device. Damage: Minor, Recharge: Fast",
      "display_short_help": "Melee, Minor DMG(Smash)",
      "display_info": {
        "Available Level": "1",
        "Power Range": "7 ft.",
        "Power Type": "Click",
        "Activation Time": "1.67s",
        "Target Type": "Enemies",
        "Effect Area": "Single Target",
        "Recharge Time": "4s",
        "Endurance Cost": "5.20",
        "Attack Types": "Melee, Smashing"
      },
      "attack_types": [
        "Melee_Def",
        "Smashing_Def"
      ],
      "enhancements_allowed": [
        "Reduce Endurance Cost",
        "Enhance Disorient",
        "Enhance Recharge Speed",
        "Enhance Damage",
        "Enhance Accuracy"
      ],
      "enhancement_set_categories_allowed": [
        "Soldiers of Arachnos Archetype Sets",
        "Stuns",
        "Universal Damage Sets",
        "Melee Damage"
      ],
      "available_at_level": 1,
      "auto_issue": false,
      "power_type": "Click",
      "accuracy": 1.0,
      "effect_area": {
        "area": "SingleTarget",
        "range_feet": 7.0
      },
      "target_type_tags": [
        "Foe"
      ],
      "display_target_type": "Enemies",
      "requires_line_of_sight": true,
      "modes_disallowed": [
        "Disable_All"
      ],
      "activate": {
        "cast_time": 1.67,
        "animation_time": 1.67,
        "animation_time_before_hit": 0.7,
        "recharge_time": 4.0,
        "endurance_cost": 5.2
      },
      "effect_groups": [
        {
          "pve_or_pvp": "PVE",
          "visible_in_info_window": true,
          "chance_percent": 100.0,
          "requires": [
            "target>enttype == critter"
          ],
          "effects": [
            {
              "attributes": [
                "Smashing_Dmg"
              ],
              "applies_to": "AbsoluteValue",
              "application_type": "Immediate",
              "target_type": "Affected",
              "magnitude": 1.0,
              "duration": "Instant",
              "flags": [
                "ResistMagnitude",
                "CombatModMagnitude"
              ],
              "stacking": {
                "behavior": "Stack",
                "by_caster": true
              },
              "scaled": [
                {
                  "archetype": "Arachnos Soldier",
                  "damage": 55.61,
                  "average": 55.61,
                  "per_activation": 33.3,
                  "per_cast_cycle": 9.81,
                  "display_info": [
                    "55.61 smashing damage on target"
                  ],
                  "base_value": -55.6102,
                  "scale": 1.0
                }
              ]
            }
          ]
        },
        {
          "pve_or_pvp": "PVE",
          "visible_in_info_window": true,
          "chance_percent": 100.0,
          "requires": [
            "(source>kMeter > 0) && (target>enttype == critter)"
          ],
          "effects": [
            {
              "attributes": [
                "Smashing_Dmg"
              ],
              "applies_to": "AbsoluteValue",
              "application_type": "Immediate",
              "target_type": "Affected",
              "magnitude": 1.0,
              "duration": "Instant",
              "flags": [
                "ResistMagnitude",
                "CombatModMagnitude"
              ],
              "stacking": {
                "behavior": "Stack",
                "by_caster": true
              },
              "scaled": [
                {
                  "archetype": "Arachnos Soldier",
                  "damage": 37.08,
                  "average": 37.08,
                  "per_activation": 22.2,
                  "per_cast_cycle": 6.54,
                  "display_info": [
                    "37.08 smashing damage on target",
                    "Only if hidden or target placated"
                  ],
                  "base_value": -55.6102,
                  "scale": 0.6667
                }
              ]
            }
          ]
        },
        {
          "pve_or_pvp": "PVP",
          "visible_in_info_window": true,
          "chance_percent": 100.0,
          "requires": [
            "target>enttype == player"
          ],
          "effects": [
            {
              "attributes": [
                "Smashing_Dmg"
              ],
              "applies_to": "AbsoluteValue",
              "application_type": "Immediate",
              "target_type": "Affected",
              "magnitude": 1.0,
              "duration": "Instant",
              "flags": [
                "ResistMagnitude",
                "CombatModMagnitude"
              ],
              "stacking": {
                "behavior": "Stack",
                "by_caster": true
              },
              "scaled": [
                {
                  "archetype": "Arachnos Soldier",
                  "damage": 97.54,
                  "average": 97.54,
                  "per_activation": 58.41,
                  "per_cast_cycle": 17.2,
                  "display_info": [
                    "97.54 smashing damage on target"
                  ],
                  "base_value": -56.4121,
                  "scale": 1.729
                }
              ]
            }
          ]
        },
        {
          "pve_or_pvp": "PVP",
          "visible_in_info_window": true,
          "chance_percent": 100.0,
          "requires": [
            "(source>kMeter > 0) && (target>enttype == player)"
          ],
          "effects": [
            {
              "attributes": [
                "Smashing_Dmg"
              ],
              "applies_to": "AbsoluteValue",
              "application_type": "Immediate",
              "target_type": "Affected",
              "magnitude": 1.0,
              "duration": "Instant",
              "flags": [
                "ResistMagnitude",
                "CombatModMagnitude"
              ],
              "stacking": {
                "behavior": "Stack",
                "by_caster": true
              },
              "scaled": [
                {
                  "archetype": "Arachnos Soldier",
                  "damage": 65.05,
                  "average": 65.05,
                  "per_activation": 38.95,
                  "per_cast_cycle": 11.47,
                  "display_info": [
                    "65.05 smashing damage on target",
                    "Only if hidden or target placated"
                  ],
                  "base_value": -56.4121,
                  "scale": 1.1532
                }
              ]
            }
          ]
        },
        {
          "pve_or_pvp": "PVE",
          "visible_in_info_window": true,
          "chance_percent": 66.0,
          "requires": [
            "target>enttype == critter"
          ],
          "effects": [
            {
              "attributes": [
                "Stunned"
              ],
              "applies_to": "CurrentModifier",
              "application_type": "OnTick",
              "target_type": "Affected",
              "magnitude": 3.0,
              "duration": "InSecondsScaled",
              "flags": [
                "ResistDuration",
                "CombatModDuration"
              ],
              "stacking": {
                "behavior": "Stack",
                "by_caster": true
              },
              "scaled": [
                {
                  "archetype": "Arachnos Soldier",
                  "duration_seconds": 8.05,
                  "display_info": [
                    "66.00% chance for 3.0 stun for 8.05s on target"
                  ],
                  "base_value": 1.341,
                  "scale": 6.0
                }
              ]
            }
          ]
        },
        {
          "pve_or_pvp": "PVP",
          "visible_in_info_window": true,
          "chance_percent": 66.0,
          "requires": [
            "target>enttype == player"
          ],
          "effects": [
            {
              "attributes": [
                "Stunned"
              ],
              "applies_to": "CurrentModifier",
              "application_type": "OnTick",
              "target_type": "Affected",
              "magnitude": 3.0,
              "duration": "InSecondsScaled",
              "flags": [
                "ResistDuration",
                "CombatModDuration"
              ],
              "stacking": {
                "behavior": "Stack",
                "by_caster": true
              },
              "scaled": [
                {
                  "archetype": "Arachnos Soldier",
                  "duration_seconds": 2.0,
                  "display_info": [
                    "66.00% chance for 3.0 stun for 2s on target"
                  ],
                  "base_value": 2.0,
                  "scale": 1.0
                }
              ]
            }
          ]
        }
      ]
    },
    {
      "name": "Arachnos_Soldiers.Arachnos_Soldier.Burst",
      "display_name": "Burst",
      "icon": "https://reborn-team.github.io/PowersAPI/assets/powers/69/arachnossoldier_burst.png",
      "display_help": "Quickly fires a Burst of rounds at a single target at long range. Damage is average, but the fire rate is fast. Can also reduce the target's defense. Damage: Moderate(DoT), Recharge: Moderate",
      "display_short_help": "Ranged, Moderate DMG(Lethal), Foe -DEF",
      "display_info": {
        "Target Type": "Enemies",
        "Endurance Cost": "8.53",
        "Available Level": "2",
        "Power Type": "Click",
        "Effect Area": "Single Target",
        "Attack Types": "Ranged, Lethal",
        "Recharge Time": "8s",
        "Activation Time": "1s",
        "Power Range": "80 ft."
      },
      "attack_types": [
        "Ranged_Def",
        "Lethal_Def"
      ],
      "enhancements_allowed": [
        "Reduce Endurance Cost",
        "Enhance Range",
        "Enhance Recharge Speed",
        "Enhance Defense DeBuff",
        "Enhance Damage",
        "Enhance Accuracy"
      ],
      "enhancement_set_categories_allowed": [
        "Accurate Defense Debuff",
        "Defense Debuff",
        "Ranged Damage",
        "Universal Damage Sets",
        "Soldiers of Arachnos Archetype Sets"
      ],
      "available_at_level": 2,
      "auto_issue": false,
      "power_type": "Click",
      "accuracy": 1.0,
      "effect_area": {
        "area": "SingleTarget",
        "range_feet": 80.0
      },
      "target_type_tags": [
        "Foe"
      ],
      "display_target_type": "Enemies",
      "requires_line_of_sight": true,
      "modes_disallowed": [
        "Disable_All"
      ],
      "activate": {
        "cast_time": 1.0,
        "animation_time": 1.0,
        "animation_time_before_hit": 0.27,
        "recharge_time": 8.0,
        "endurance_cost": 8.53
      },
      "effect_groups": [
        {
          "pve_or_pvp": "PVE",
          "visible_in_info_window": true,
          "chance_percent": 100.0,
          "requires": [
            "target>enttype == critter"
          ],
          "effects": [
            {
              "attributes": [
                "Lethal_Dmg"
              ],
              "applies_to": "AbsoluteValue",
              "application_type": "OnTick",
              "tick_chance_percent": 100.0,
              "target_type": "Affected",
              "magnitude": 1.0,
              "duration": "InSeconds",
              "duration_seconds": 0.7,
              "continuous_apply_seconds": 0.3,
              "ticks": 3,
              "flags": [
                "ResistMagnitude",
                "CombatModMagnitude"
              ],
              "stacking": {
                "behavior": "Stack",
                "by_caster": true
              },
              "scaled": [
                {
                  "archetype": "Arachnos Soldier",
                  "damage": 30.4,
                  "average": 30.4,
                  "per_activation": 30.4,
                  "per_cast_cycle": 3.38,
                  "display_info": [
                    "3 ticks of 30.40 lethal damage over 0.7s on target"
                  ],
                  "base_value": -55.6102,
                  "scale": 0.5467
                }
              ]
            }
          ]
        },
        {
          "visible_in_info_window": true,
          "chance_percent": 100.0,
          "effects": [
            {
              "attributes": [
                "Defense"
              ],
              "applies_to": "CurrentValue",
              "application_type": "OnTick",
              "tick_chance_percent": 100.0,
              "target_type": "Affected",
              "magnitude": 1.0,
              "duration": "InSeconds",
              "duration_seconds": 8.0,
              "flags": [
                "ResistMagnitude",
                "CombatModMagnitude"
              ],
              "stacking": {
                "behavior": "Stack",
                "by_caster": true
              },
              "scaled": [
                {
                  "archetype": "Arachnos Soldier",
                  "percent": -7.5,
                  "display_info": [
                    "-7.50% strength to defense for 8s on target"
                  ],
                  "base_value": -0.075,
                  "scale": 1.0
                }
              ]
            }
          ]
        },
        {
          "pve_or_pvp": "PVP",
          "visible_in_info_window": true,
          "chance_percent": 100.0,
          "requires": [
            "target>enttype == player"
          ],
          "effects": [
            {
              "attributes": [
                "Lethal_Dmg"
              ],
              "applies_to": "AbsoluteValue",
              "application_type": "OnTick",
              "tick_chance_percent": 100.0,
              "target_type": "Affected",
              "magnitude": 1.0,
              "duration": "InSeconds",
              "duration_seconds": 0.7,
              "continuous_apply_seconds": 0.3,
              "ticks": 3,
              "flags": [
                "ResistMagnitude",
                "CombatModMagnitude"
              ],
              "stacking": {
                "behavior": "Stack",
                "by_caster": true
              },
              "scaled": [
                {
                  "archetype": "Arachnos Soldier",
                  "damage": 26.44,
                  "average": 26.44,
                  "per_activation": 26.44,
                  "per_cast_cycle": 2.94,
                  "display_info": [
                    "3 ticks of 26.44 lethal damage over 0.7s on target"
                  ],
                  "base_value": -56.4132,
                  "scale": 0.4686
                }
              ]
            }
          ]
        }
      ]
    },
    {
      "name": "Arachnos_Soldiers.Arachnos_Soldier.WS_Wide_Area_Web_Grenade",
      "display_name": "Wide Area Web Grenade",
      "icon": "https://reborn-team.github.io/PowersAPI/assets/powers/62/arachnossoldier_wideareawebgrenade.png",
      "display_help": "Launches a Grenade at long range from under the barrel of your Assault rifle. It explodes into a field of sticky webs which slow and can immobilize all foes within its radius. Recharge: Slow",
      "display_short_help": "Ranged (Targeted AoE), Immobilize, -Fly, -Recharge",
      "display_info": {
        "Power Range": "80 ft.",
        "Available Level": "6",
        "Activation Time": "1.67s",
        "Endurance Cost": "7.28",
        "Attack Types": "Area",
        "Effect Area": "AoE — 10 ft. radius (10 targets max)",
        "Power Type": "Click",
        "Target Type": "Enemies",
        "Recharge Time": "30s"
      },
      "attack_types": [
        "Area_Def"
      ],
      "enhancements_allowed": [
        "Reduce Endurance Cost",
        "Enhance Range",
        "Enhance Recharge Speed",
        "Enhance Immobilization",
        "Enhance Accuracy"
      ],
      "enhancement_set_categories_allowed": [
        "Immobilize"
      ],
      "available_at_level": 6,
      "auto_issue": false,
      "power_type": "Click",
      "accuracy": 1.0,
      "effect_area": {
        "area": "AoE",
        "max_targets_hit": 10,
        "radius_feet": 10.0,
        "range_feet": 80.0
      },
      "target_type_tags": [
        "Foe"
      ],
      "display_target_type": "Enemies",
      "requires_line_of_sight": true,
      "modes_disallowed": [
        "Disable_All"
      ],
      "activate": {
        "cast_time": 1.67,
        "animation_time": 1.67,
        "animation_time_before_hit": 0.4,
        "recharge_time": 30.0,
        "endurance_cost": 7.28
      },
      "effect_groups": [
        {
          "pve_or_pvp": "PVE",
          "visible_in_info_window": true,
          "chance_percent": 100.0,
          "requires": [
            "target>enttype == critter"
          ],
          "effects": [
            {
              "attributes": [
                "Immobilized"
              ],
              "applies_to": "CurrentModifier",
              "application_type": "OnTick",
              "target_type": "Affected",
              "magnitude": 3.0,
              "duration": "InSecondsScaled",
              "flags": [
                "ResistDuration",
                "CombatModDuration"
              ],
              "stacking": {
                "behavior": "Stack",
                "by_caster": true
              },
              "scaled": [
                {
                  "archetype": "Arachnos Soldier",
                  "duration_seconds": 20.12,
                  "display_info": [
                    "3.0 immobilize for 20.12s on target"
                  ],
                  "base_value": 1.341,
                  "scale": 15.0
                }
              ]
            }
          ]
        },
        {
          "pve_or_pvp": "PVP",
          "visible_in_info_window": true,
          "chance_percent": 100.0,
          "requires": [
            "target>enttype == player"
          ],
          "effects": [
            {
              "attributes": [
                "Immobilized"
              ],
              "applies_to": "CurrentModifier",
              "application_type": "OnTick",
              "target_type": "Affected",
              "magnitude": 3.0,
              "duration": "InSecondsScaled",
              "flags": [
                "ResistDuration",
                "CombatModDuration"
              ],
              "stacking": {
                "behavior": "Stack",
                "by_caster": true
              },
              "scaled": [
                {
                  "archetype": "Arachnos Soldier",
                  "duration_seconds": 2.0,
                  "display_info": [
                    "3.0 immobilize for 2s on target"
                  ],
                  "base_value": 2.0,
                  "scale": 1.0
                }
              ]
            }
          ]
        },
        {
          "visible_in_info_window": true,
          "chance_percent": 100.0,
          "effects": [
            {
              "attributes": [
                "RechargeTime"
              ],
              "applies_to": "Strength",
              "application_type": "OnTick",
              "tick_chance_percent": 100.0,
              "target_type": "Affected",
              "magnitude": 1.0,
              "duration": "InSeconds",
              "duration_seconds": 15.0,
              "flags": [
                "NearGround",
                "IgnoreStrength",
                "ResistMagnitude",
                "CombatModMagnitude"
              ],
              "stacking": {
                "behavior": "Replace",
                "by_caster": true
              },
              "scaled": [
                {
                  "archetype": "Arachnos Soldier",
                  "percent": -50.0,
                  "display_info": [
                    "-50.00% strength to recharge for 15s on target",
                    "Ignores buffs and enhancements"
                  ],
                  "base_value": -1.0,
                  "scale": 0.5
                }
              ]
            },
            {
              "attributes": [
                "RunningSpeed",
                "FlyingSpeed"
              ],
              "applies_to": "CurrentValue",
              "application_type": "OnTick",
              "tick_chance_percent": 100.0,
              "target_type": "Affected",
              "magnitude": 1.0,
              "duration": "InSeconds",
              "duration_seconds": 15.0,
              "flags": [
                "NearGround",
                "ResistMagnitude",
                "CombatModMagnitude"
              ],
              "stacking": {
                "behavior": "Replace",
                "by_caster": true
              },
              "scaled": [
                {
                  "archetype": "Arachnos Soldier",
                  "percent": -50.0,
                  "display_info": [
                    "-50.00% run speed, fly speed for 15s on target"
                  ],
                  "base_value": -1.0,
                  "scale": 0.5
                }
              ]
            },
            {
              "attributes": [
                "Knockup",
                "Knockback"
              ],
              "applies_to": "Resistance",
              "application_type": "OnTick",
              "tick_chance_percent": 100.0,
              "target_type": "Affected",
              "magnitude": 1.0,
              "duration": "InSeconds",
              "duration_seconds": 15.0,
              "flags": [
                "IgnoreResistance",
                "CombatModMagnitude"
              ],
              "stacking": {
                "behavior": "Stack",
                "by_caster": true
              },
              "scaled": [
                {
                  "archetype": "Arachnos Soldier",
                  "percent": 10000.0,
                  "display_info": [
                    "10000.00% resistance to knockup, knock for 15s on target",
                    "Unresistable"
                  ],
                  "base_value": 1.0,
                  "scale": 100.0
                }
              ]
            },
            {
              "attributes": [
                "Knockup",
                "Knockback"
              ],
              "applies_to": "CurrentModifier",
              "application_type": "OnTick",
              "tick_chance_percent": 100.0,
              "target_type": "Affected",
              "duration": "InSeconds",
              "duration_seconds": 15.0,
              "flags": [
                "IgnoreResistance",
                "CombatModMagnitude"
              ],
              "stacking": {
                "behavior": "Stack",
                "by_caster": true
              },
              "scaled": [
                {
                  "archetype": "Arachnos Soldier",
                  "magnitude": -100.0,
                  "display_info": [
                    "-100.0 knockup protection, knock protection for 15s on target",
                    "Unresistable"
                  ],
                  "base_value": 1.0,
                  "scale": -100.0
                }
              ]
            },
            {
              "attributes": [
                "JumpHeight"
              ],
              "applies_to": "CurrentValue",
              "application_type": "OnTick",
              "tick_chance_percent": 100.0,
              "target_type": "Affected",
              "magnitude": 1.0,
              "duration": "InSeconds",
              "duration_seconds": 15.0,
              "flags": [
                "IgnoreResistance",
                "CombatModMagnitude"
              ],
              "stacking": {
                "behavior": "Stack",
                "by_caster": true
              },
              "scaled": [
                {
                  "archetype": "Arachnos Soldier",
                  "percent": -50000.0,
                  "display_info": [
                    "-50000.00% jump height for 15s on target",
                    "Unresistable"
                  ],
                  "base_value": 1.0,
                  "scale": -500.0
                }
              ]
            },
            {
              "attributes": [
                "Fly"
              ],
              "applies_to": "CurrentValue",
              "application_type": "OnTick",
              "tick_chance_percent": 100.0,
              "target_type": "Affected",
              "duration": "InSeconds",
              "duration_seconds": 15.0,
              "flags": [
                "IgnoreResistance",
                "CombatModMagnitude"
              ],
              "stacking": {
                "behavior": "Stack",
                "by_caster": true
              },
              "scaled": [
                {
                  "archetype": "Arachnos Soldier",
                  "magnitude": -10.0,
                  "display_info": [
                    "-10.0 fly protection for 15s on target",
                    "Unresistable"
                  ],
                  "base_value": 1.0,
                  "scale": -10.0
                }
              ]
            }
          ]
        }
      ]
    },
    {
      "name": "Arachnos_Soldiers.Arachnos_Soldier.Heavy_Burst",
      "display_name": "Heavy Burst",
      "icon": "https://reborn-team.github.io/PowersAPI/assets/powers/cc/arachnossoldier_heavyburst.png",
      "display_help": "Fires a Heavy Burst of rounds at foes in a long cone in front of the user. Can also reduce the targets' defense. Damage: Moderate(DoT), Recharge: Slow",
      "display_short_help": "Ranged Cone, Moderate DMG(Lethal), Foe -DEF",
      "display_info": {
        "Available Level": "8",
        "Endurance Cost": "11.86",
        "Recharge Time": "12s",
        "Power Type": "Click",
        "Attack Types": "Ranged, Lethal",
        "Effect Area": "Cone — 50 ft. radius 30° arc (10 targets max)",
        "Target Type": "Enemies",
        "Power Range": "50 ft.",
        "Activation Time": "2.67s"
      },
      "attack_types": [
        "Ranged_Def",
        "Lethal_Def"
      ],
      "enhancements_allowed": [
        "Reduce Endurance Cost",
        "Enhance Range",
        "Enhance Recharge Speed",
        "Enhance Defense DeBuff",
        "Enhance Damage",
        "Enhance Accuracy"
      ],
      "enhancement_set_categories_allowed": [
        "Accurate Defense Debuff",
        "Universal Damage Sets",
        "Defense Debuff",
        "Soldiers of Arachnos Archetype Sets",
        "Targeted AoE Damage"
      ],
      "available_at_level": 8,
      "auto_issue": false,
      "power_type": "Click",
      "accuracy": 1.0,
      "effect_area": {
        "area": "Cone",
        "max_targets_hit": 10,
        "radius_feet": 50.0,
        "arc_degrees": 30.0,
        "range_feet": 50.0
      },
      "target_type_tags": [
        "Foe"
      ],
      "display_target_type": "Enemies",
      "requires_line_of_sight": true,
      "modes_disallowed": [
        "Disable_All"
      ],
      "activate": {
        "cast_time": 2.67,
        "animation_time": 2.67,
        "animation_time_before_hit": 0.27,
        "recharge_time": 12.0,
        "endurance_cost": 11.86
      },
      "effect_groups": [
        {
          "pve_or_pvp": "PVE",
          "visible_in_info_window": true,
          "chance_percent": 100.0,
          "requires": [
            "target>enttype == critter"
          ],
          "effects": [
            {
              "attributes": [
                "Lethal_Dmg"
              ],
              "applies_to": "AbsoluteValue",
              "application_type": "OnTick",
              "tick_chance_percent": 100.0,
              "target_type": "Affected",
              "magnitude": 1.0,
              "duration": "InSeconds",
              "duration_seconds": 2.0,
              "continuous_apply_seconds": 0.3,
              "ticks": 7,
              "flags": [
                "ResistMagnitude",
                "CombatModMagnitude"
              ],
              "stacking": {
                "behavior": "Stack",
                "by_caster": true
              },
              "scaled": [
                {
                  "archetype": "Arachnos Soldier",
                  "damage": 8.66,
                  "average": 8.66,
                  "per_activation": 3.24,
                  "per_cast_cycle": 0.59,
                  "display_info": [
                    "7 ticks of 8.66 lethal damage over 2s on target"
                  ],
                  "base_value": -55.6102,
                  "scale": 0.1557
                }
              ]
            }
          ]
        },
        {
          "visible_in_info_window": true,
          "chance_percent": 100.0,
          "effects": [
            {
              "attributes": [
                "Defense"
              ],
              "applies_to": "CurrentValue",
              "application_type": "OnTick",
              "tick_chance_percent": 100.0,
              "target_type": "Affected",
              "magnitude": 1.0,
              "duration": "InSeconds",
              "duration_seconds": 12.0,
              "flags": [
                "ResistMagnitude",
                "CombatModMagnitude"
              ],
              "stacking": {
                "behavior": "Stack",
                "by_caster": true
              },
              "scaled": [
                {
                  "archetype": "Arachnos Soldier",
                  "percent": -7.5,
                  "display_info": [
                    "-7.50% strength to defense for 12s on target"
                  ],
                  "base_value": -0.075,
                  "scale": 1.0
                }
              ]
            }
          ]
        },
        {
          "pve_or_pvp": "PVP",
          "visible_in_info_window": true,
          "chance_percent": 100.0,
          "requires": [
            "target>enttype == player"
          ],
          "effects": [
            {
              "attributes": [
                "Lethal_Dmg"
              ],
              "applies_to": "AbsoluteValue",
              "application_type": "OnTick",
              "tick_chance_percent": 100.0,
              "target_type": "Affected",
              "magnitude": 1.0,
              "duration": "InSeconds",
              "duration_seconds": 2.0,
              "continuous_apply_seconds": 0.3,
              "ticks": 7,
              "flags": [
                "ResistMagnitude",
                "CombatModMagnitude"
              ],
              "stacking": {
                "behavior": "Stack",
                "by_caster": true
              },
              "scaled": [
                {
                  "archetype": "Arachnos Soldier",
                  "damage": 9.04,
                  "average": 9.04,
                  "per_activation": 3.39,
                  "per_cast_cycle": 0.62,
                  "display_info": [
                    "7 ticks of 9.04 lethal damage over 2s on target"
                  ],
                  "base_value": -56.4132,
                  "scale": 0.1603
                }
              ]
            }
          ]
        }
      ]
    },
    {
      "name": "Arachnos_Soldiers.Arachnos_Soldier.Bayonet",
      "display_name": "Bayonet",
      "icon": "https://reborn-team.github.io/PowersAPI/assets/powers/d7/arachnossoldier_bayonet.png",
      "display_help": "Your weapon includes a bayonet attachment which you can use to stab at your enemies for lethal damage as well as causing them to bleed losing health over time. NOTE: This power will deal critical damage if used after a successful Placate or while the user is hidden with the Bane Spider Cloaking Device. Damage: Moderate, Recharge: Moderate",
      "display_short_help": "Melee, Moderate DMG(Lethal), DoT(Lethal)",
      "display_info": {
        "Recharge Time": "8s",
        "Endurance Cost": "8.53",
        "Power Type": "Click",
        "Power Range": "7 ft.",
        "Attack Types": "Melee, Smashing",
        "Available Level": "12",
        "Target Type": "Enemies",
        "Activation Time": "1.67s",
        "Effect Area": "Single Target"
      },
      "attack_types": [
        "Melee_Def",
        "Smashing_Def"
      ],
      "enhancements_allowed": [
        "Reduce Endurance Cost",
        "Enhance Recharge Speed",
        "Enhance Damage",
        "Enhance Accuracy"
      ],
      "enhancement_set_categories_allowed": [
        "Soldiers of Arachnos Archetype Sets",
        "Melee Damage",
        "Universal Damage Sets"
      ],
      "available_at_level": 12,
      "auto_issue": false,
      "power_type": "Click",
      "accuracy": 1.0,
      "effect_area": {
        "area": "SingleTarget",
        "range_feet": 7.0
      },
      "target_type_tags": [
        "Foe"
      ],
      "display_target_type": "Enemies",
      "requires_line_of_sight": true,
      "modes_disallowed": [
        "Disable_All"
      ],
      "activate": {
        "cast_time": 1.67,
        "animation_time": 1.67,
        "animation_time_before_hit": 0.53,
        "recharge_time": 8.0,
        "endurance_cost": 8.53
      },
      "effect_groups": [
        {
          "pve_or_pvp": "PVE",
          "visible_in_info_window": true,
          "chance_percent": 100.0,
          "requires": [
            "target>enttype == critter"
          ],
          "effects": [
            {
              "attributes": [
                "Lethal_Dmg"
              ],
              "applies_to": "AbsoluteValue",
              "application_type": "Immediate",
              "target_type": "Affected",
              "magnitude": 1.0,
              "duration": "Instant",
              "flags": [
                "ResistMagnitude",
                "CombatModMagnitude"
              ],
              "stacking": {
                "behavior": "Stack",
                "by_caster": true
              },
              "scaled": [
                {
                  "archetype": "Arachnos Soldier",
                  "damage": 80.08,
                  "average": 80.08,
                  "per_activation": 47.95,
                  "per_cast_cycle": 8.28,
                  "display_info": [
                    "80.08 lethal damage on target"
                  ],
                  "base_value": -55.6102,
                  "scale": 1.44
                }
              ]
            }
          ]
        },
        {
          "pve_or_pvp": "PVE",
          "visible_in_info_window": true,
          "chance_percent": 100.0,
          "requires": [
            "(source>kMeter > 0) && (target>enttype == critter)"
          ],
          "effects": [
            {
              "attributes": [
                "Lethal_Dmg"
              ],
              "applies_to": "AbsoluteValue",
              "application_type": "Immediate",
              "target_type": "Affected",
              "magnitude": 1.0,
              "duration": "Instant",
              "flags": [
                "ResistMagnitude",
                "CombatModMagnitude"
              ],
              "stacking": {
                "behavior": "Stack",
                "by_caster": true
              },
              "scaled": [
                {
                  "archetype": "Arachnos Soldier",
                  "damage": 53.39,
                  "average": 53.39,
                  "per_activation": 31.97,
                  "per_cast_cycle": 5.52,
                  "display_info": [
                    "53.39 lethal damage on target",
                    "Only if hidden or target placated"
                  ],
                  "base_value": -55.6102,
                  "scale": 0.96
                }
              ]
            }
          ]
        },
        {
          "pve_or_pvp": "PVP",
          "visible_in_info_window": true,
          "chance_percent": 100.0,
          "requires": [
            "target>enttype == player"
          ],
          "effects": [
            {
              "attributes": [
                "Lethal_Dmg"
              ],
              "applies_to": "AbsoluteValue",
              "application_type": "Immediate",
              "target_type": "Affected",
              "magnitude": 1.0,
              "duration": "Instant",
              "flags": [
                "ResistMagnitude",
                "CombatModMagnitude"
              ],
              "stacking": {
                "behavior": "Stack",
                "by_caster": true
              },
              "scaled": [
                {
                  "archetype": "Arachnos Soldier",
                  "damage": 106.56,
                  "average": 106.56,
                  "per_activation": 63.81,
                  "per_cast_cycle": 11.02,
                  "display_info": [
                    "106.56 lethal damage on target"
                  ],
                  "base_value": -56.4121,
                  "scale": 1.8889
                }
              ]
            }
          ]
        },
        {
          "pve_or_pvp": "PVP",
          "visible_in_info_window": true,
          "chance_percent": 100.0,
          "requires": [
            "(source>kMeter > 0) && (target>enttype == player)"
          ],
          "effects": [
            {
              "attributes": [
                "Lethal_Dmg"
              ],
              "applies_to": "AbsoluteValue",
              "application_type": "Immediate",
              "target_type": "Affected",
              "magnitude": 1.0,
              "duration": "Instant",
              "flags": [
                "ResistMagnitude",
                "CombatModMagnitude"
              ],
              "stacking": {
                "behavior": "Stack",
                "by_caster": true
              },
              "scaled": [
                {
                  "archetype": "Arachnos Soldier",
                  "damage": 71.07,
                  "average": 71.07,
                  "per_activation": 42.56,
                  "per_cast_cycle": 7.35,
                  "display_info": [
                    "71.07 lethal damage on target",
                    "Only if hidden or target placated"
                  ],
                  "base_value": -56.4121,
                  "scale": 1.2599
                }
              ]
            }
          ]
        },
        {
          "visible_in_info_window": true,
          "chance_percent": 100.0,
          "effects": [
            {
              "attributes": [
                "Lethal_Dmg"
              ],
              "applies_to": "AbsoluteValue",
              "application_type": "OnTick",
              "tick_chance_percent": 100.0,
              "target_type": "Affected",
              "magnitude": 1.0,
              "duration": "InSeconds",
              "duration_seconds": 5.1,
              "after_delay_seconds": 0.5,
              "continuous_apply_seconds": 1.0,
              "ticks": 6,
              "flags": [
                "ResistMagnitude",
                "CombatModMagnitude"
              ],
              "stacking": {
                "behavior": "Stack",
                "by_caster": true
              },
              "scaled": [
                {
                  "archetype": "Arachnos Soldier",
                  "damage": 6.67,
                  "average": 6.67,
                  "per_activation": 3.99,
                  "per_cast_cycle": 0.69,
                  "display_info": [
                    "6 ticks of 6.67 lethal damage over 5.1s on target after 0.5s delay"
                  ],
                  "base_value": -55.6102,
                  "scale": 0.12
                }
              ]
            }
          ]
        }
      ]
    },
    {
      "name": "Arachnos_Soldiers.Arachnos_Soldier.Venom_Grenade",
      "display_name": "Venom Grenade",
      "icon": "https://reborn-team.github.io/PowersAPI/assets/powers/32/arachnossoldier_venomgrenade.png",
      "display_help": "This poisonous grenade causes toxic damage over time and weakens the resistance of all foes within the area of effect. NOTE: If you take this power you cannot also take the Crab Spider version. Damage: Moderate, Recharge: Slow",
      "display_short_help": "Ranged(Targeted AoE), DoT(Toxic), -Res(All)",
      "display_info": {
        "Target Type": "Enemies",
        "Recharge Time": "24s",
        "Effect Area": "AoE — 20 ft. radius (10 targets max)",
        "Attack Types": "Area",
        "Activation Time": "1.67s",
        "Available Level": "12",
        "Power Type": "Click",
        "Endurance Cost": "11.86",
        "Power Range": "80 ft."
      },
      "requires": "!Arachnos_Soldiers.Crab_Spider_Soldier.CS_Venom_Grenade",
      "attack_types": [
        "Area_Def"
      ],
      "enhancements_allowed": [
        "Reduce Endurance Cost",
        "Enhance Range",
        "Enhance Recharge Speed",
        "Enhance Damage",
        "Enhance Accuracy"
      ],
      "enhancement_set_categories_allowed": [
        "Soldiers of Arachnos Archetype Sets",
        "Universal Damage Sets",
        "Targeted AoE Damage"
      ],
      "available_at_level": 12,
      "auto_issue": false,
      "power_type": "Click",
      "accuracy": 1.0,
      "effect_area": {
        "area": "AoE",
        "max_targets_hit": 10,
        "radius_feet": 20.0,
        "range_feet": 80.0
      },
      "target_type_tags": [
        "Foe"
      ],
      "display_target_type": "Enemies",
      "requires_line_of_sight": true,
      "modes_disallowed": [
        "Disable_All"
      ],
      "activate": {
        "cast_time": 1.67,
        "animation_time": 1.67,
        "animation_time_before_hit": 0.4,
        "recharge_time": 24.0,
        "endurance_cost": 11.86
      },
      "effect_groups": [
        {
          "pve_or_pvp": "PVE",
          "visible_in_info_window": true,
          "chance_percent": 100.0,
          "requires": [
            "target>enttype == critter"
          ],
          "effects": [
            {
              "attributes": [
                "Toxic_Dmg"
              ],
              "applies_to": "AbsoluteValue",
              "application_type": "OnTick",
              "tick_chance_percent": 100.0,
              "target_type": "Affected",
              "magnitude": 1.0,
              "duration": "InSeconds",
              "duration_seconds": 4.125,
              "continuous_apply_seconds": 1.0,
              "ticks": 5,
              "flags": [
                "ResistMagnitude",
                "CombatModMagnitude"
              ],
              "stacking": {
                "behavior": "Stack",
                "by_caster": true
              },
              "scaled": [
                {
                  "archetype": "Arachnos Soldier",
                  "damage": 10.92,
                  "average": 10.92,
                  "per_activation": 6.54,
                  "per_cast_cycle": 0.43,
                  "display_info": [
                    "5 ticks of 10.92 toxic damage over 4.13s on target"
                  ],
                  "base_value": -55.6102,
                  "scale": 0.1964
                }
              ]
            }
          ]
        },
        {
          "visible_in_info_window": true,
          "chance_percent": 100.0,
          "effects": [
            {
              "attributes": [
                "Smashing_Dmg",
                "Lethal_Dmg",
                "Fire_Dmg",
                "Cold_Dmg",
                "Energy_Dmg",
                "Negative_Energy_Dmg",
                "Psionic_Dmg",
                "Toxic_Dmg"
              ],
              "applies_to": "Resistance",
              "application_type": "OnTick",
              "tick_chance_percent": 100.0,
              "target_type": "Affected",
              "magnitude": 1.0,
              "duration": "InSeconds",
              "duration_seconds": 16.0,
              "flags": [
                "IgnoreStrength",
                "ResistMagnitude",
                "CombatModMagnitude"
              ],
              "stacking": {
                "behavior": "Replace",
                "by_caster": true
              },
              "scaled": [
                {
                  "archetype": "Arachnos Soldier",
                  "percent": -20.0,
                  "display_info": [
                    "-20.00% resistance to smashing damage, lethal damage, fire damage, cold damage, energy damage, negative energy damage, psionic damage, toxic damage for 16s on target",
                    "Ignores buffs and enhancements"
                  ],
                  "base_value": 0.1,
                  "scale": -2.0
                }
              ]
            },
            {
              "attributes": [
                "Toxic_Dmg"
              ],
              "applies_to": "Resistance",
              "application_type": "OnTick",
              "tick_chance_percent": 100.0,
              "target_type": "Affected",
              "magnitude": 1.0,
              "duration": "InSeconds",
              "duration_seconds": 16.0,
              "flags": [
                "IgnoreStrength",
                "ResistMagnitude",
                "CombatModMagnitude"
              ],
              "stacking": {
                "behavior": "Replace",
                "by_caster": true
              },
              "scaled": [
                {
                  "archetype": "Arachnos Soldier",
                  "percent": -40.0,
                  "display_info": [
                    "-40.00% resistance to toxic damage for 16s on target",
                    "Ignores buffs and enhancements"
                  ],
                  "base_value": 0.1,
                  "scale": -4.0
                }
              ]
            }
          ]
        },
        {
          "pve_or_pvp": "PVP",
          "visible_in_info_window": true,
          "chance_percent": 100.0,
          "requires": [
            "target>enttype == player"
          ],
          "effects": [
            {
              "attributes": [
                "Toxic_Dmg"
              ],
              "applies_to": "AbsoluteValue",
              "application_type": "OnTick",
              "tick_chance_percent": 100.0,
              "target_type": "Affected",
              "magnitude": 1.0,
              "duration": "InSeconds",
              "duration_seconds": 4.125,
              "continuous_apply_seconds": 1.0,
              "ticks": 5,
              "flags": [
                "ResistMagnitude",
                "CombatModMagnitude"
              ],
              "stacking": {
                "behavior": "Stack",
                "by_caster": true
              },
              "scaled": [
                {
                  "archetype": "Arachnos Soldier",
                  "damage": 7.13,
                  "average": 7.13,
                  "per_activation": 4.27,
                  "per_cast_cycle": 0.28,
                  "display_info": [
                    "5 ticks of 7.13 toxic damage over 4.13s on target"
                  ],
                  "base_value": -56.4132,
                  "scale": 0.1264
                }
              ]
            }
          ]
        }
      ]
    },
    {
      "name": "Arachnos_Soldiers.Arachnos_Soldier.Frag_Grenade",
      "display_name": "Frag Grenade",
      "icon": "https://reborn-team.github.io/PowersAPI/assets/powers/51/arachnossoldier_fraggrenade.png",
      "display_help": "Launches a Frag Grenade at long range from under the barrel of your rifle. The explosion from this grenade affects all within the blast and can knock them back. Note: If you take this power, you cannot take the Crab Spider version. Damage: Moderate, Recharge: Slow",
      "display_short_help": "Ranged(Targeted AoE), Moderate DMG (Lethal/Smash), Foe Knockback",
      "display_info": {
        "Effect Area": "AoE — 10 ft. radius (10 targets max)",
        "Power Range": "80 ft.",
        "Endurance Cost": "15.18",
        "Power Type": "Click",
        "Activation Time": "1.67s",
        "Target Type": "Enemies",
        "Attack Types": "Area, Lethal, Smashing",
        "Recharge Time": "16s",
        "Available Level": "18"
      },
      "requires": "!Arachnos_Soldiers.Crab_Spider_Soldier.CS_Frag_Grenade",
      "attack_types": [
        "Area_Def",
        "Lethal_Def",
        "Smashing_Def"
      ],
      "enhancements_allowed": [
        "Reduce Endurance Cost",
        "Enhance Range",
        "Enhance Recharge Speed",
        "Enhance KnockBack",
        "Enhance Damage",
        "Enhance Accuracy"
      ],
      "enhancement_set_categories_allowed": [
        "Universal Damage Sets",
        "Targeted AoE Damage",
        "Soldiers of Arachnos Archetype Sets",
        "Knockback"
      ],
      "available_at_level": 18,
      "auto_issue": false,
      "power_type": "Click",
      "accuracy": 1.0,
      "effect_area": {
        "area": "AoE",
        "max_targets_hit": 10,
        "radius_feet": 10.0,
        "range_feet": 80.0
      },
      "target_type_tags": [
        "Foe"
      ],
      "display_target_type": "Enemies",
      "requires_line_of_sight": true,
      "modes_disallowed": [
        "Disable_All"
      ],
      "activate": {
        "cast_time": 1.67,
        "animation_time": 1.67,
        "animation_time_before_hit": 0.4,
        "recharge_time": 16.0,
        "endurance_cost": 15.18
      },
      "effect_groups": [
        {
          "pve_or_pvp": "PVE",
          "visible_in_info_window": true,
          "chance_percent": 100.0,
          "requires": [
            "target>enttype == critter"
          ],
          "effects": [
            {
              "attributes": [
                "Smashing_Dmg"
              ],
              "applies_to": "AbsoluteValue",
              "application_type": "Immediate",
              "target_type": "Affected",
              "magnitude": 1.0,
              "duration": "Instant",
              "flags": [
                "ResistMagnitude",
                "CombatModMagnitude"
              ],
              "stacking": {
                "behavior": "Stack",
                "by_caster": true
              },
              "scaled": [
                {
                  "archetype": "Arachnos Soldier",
                  "damage": 27.81,
                  "average": 27.81,
                  "per_activation": 16.65,
                  "per_cast_cycle": 1.57,
                  "display_info": [
                    "27.81 smashing damage on target"
                  ],
                  "base_value": -55.6102,
                  "scale": 0.5
                }
              ]
            },
            {
              "attributes": [
                "Lethal_Dmg"
              ],
              "applies_to": "AbsoluteValue",
              "application_type": "Immediate",
              "target_type": "Affected",
              "magnitude": 1.0,
              "duration": "Instant",
              "flags": [
                "ResistMagnitude",
                "CombatModMagnitude"
              ],
              "stacking": {
                "behavior": "Stack",
                "by_caster": true
              },
              "scaled": [
                {
                  "archetype": "Arachnos Soldier",
                  "damage": 37.26,
                  "average": 37.26,
                  "per_activation": 22.31,
                  "per_cast_cycle": 2.11,
                  "display_info": [
                    "37.26 lethal damage on target"
                  ],
                  "base_value": -55.6102,
                  "scale": 0.67
                }
              ]
            }
          ]
        },
        {
          "pve_or_pvp": "PVP",
          "visible_in_info_window": true,
          "chance_percent": 100.0,
          "requires": [
            "target>enttype == player"
          ],
          "effects": [
            {
              "attributes": [
                "Smashing_Dmg"
              ],
              "applies_to": "AbsoluteValue",
              "application_type": "Immediate",
              "target_type": "Affected",
              "magnitude": 1.0,
              "duration": "Instant",
              "flags": [
                "ResistMagnitude",
                "CombatModMagnitude"
              ],
              "stacking": {
                "behavior": "Stack",
                "by_caster": true
              },
              "scaled": [
                {
                  "archetype": "Arachnos Soldier",
                  "damage": 20.93,
                  "average": 20.93,
                  "per_activation": 12.53,
                  "per_cast_cycle": 1.18,
                  "display_info": [
                    "20.93 smashing damage on target"
                  ],
                  "base_value": -56.4132,
                  "scale": 0.3711
                }
              ]
            },
            {
              "attributes": [
                "Lethal_Dmg"
              ],
              "applies_to": "AbsoluteValue",
              "application_type": "Immediate",
              "target_type": "Affected",
              "magnitude": 1.0,
              "duration": "Instant",
              "flags": [
                "ResistMagnitude",
                "CombatModMagnitude"
              ],
              "stacking": {
                "behavior": "Stack",
                "by_caster": true
              },
              "scaled": [
                {
                  "archetype": "Arachnos Soldier",
                  "damage": 28.91,
                  "average": 28.91,
                  "per_activation": 17.31,
                  "per_cast_cycle": 1.64,
                  "display_info": [
                    "28.91 lethal damage on target"
                  ],
                  "base_value": -56.4132,
                  "scale": 0.5125
                }
              ]
            }
          ]
        },
        {
          "pve_or_pvp": "PVE",
          "visible_in_info_window": true,
          "chance_percent": 50.0,
          "requires": [
            "target>enttype == critter"
          ],
          "effects": [
            {
              "attributes": [
                "Knockback"
              ],
              "applies_to": "CurrentModifier",
              "application_type": "Immediate",
              "target_type": "Affected",
              "duration": "Instant",
              "flags": [
                "ResistMagnitude",
                "CombatModMagnitude"
              ],
              "stacking": {
                "behavior": "Stack",
                "by_caster": true
              },
              "scaled": [
                {
                  "archetype": "Arachnos Soldier",
                  "magnitude": 1.25,
                  "display_info": [
                    "50.00% chance for 1.2 magnitude knock on target"
                  ],
                  "base_value": 1.8694,
                  "scale": 0.67
                }
              ]
            }
          ]
        },
        {
          "pve_or_pvp": "PVP",
          "visible_in_info_window": true,
          "chance_percent": 50.0,
          "requires": [
            "target>enttype == player"
          ],
          "effects": [
            {
              "attributes": [
                "Knockback"
              ],
              "applies_to": "CurrentModifier",
              "application_type": "Immediate",
              "target_type": "Affected",
              "duration": "Instant",
              "flags": [
                "ResistMagnitude",
                "CombatModMagnitude"
              ],
              "stacking": {
                "behavior": "Stack",
                "by_caster": true
              },
              "scaled": [
                {
                  "archetype": "Arachnos Soldier",
                  "magnitude": 1.25,
                  "display_info": [
                    "50.00% chance for 1.2 magnitude knock on target"
                  ],
                  "base_value": 1.8694,
                  "scale": 0.67
                }
              ]
            }
          ]
        }
      ]
    }
  ]
}