{
  "issue": "i26p5",
  "source": "homecoming",
  "extract_date": "2020-08-11T21:52:57.192132400-07:00",
  "name": "Pets.LightningStorm_Controller",
  "display_name": "LightningStorm_Controller",
  "display_help": "Storm Summoning",
  "icon": "https://reborn-team.github.io/PowersAPI/assets/powers/5a/electricalbolt_lightningbolt.png",
  "show_in_inventory": "Show",
  "show_in_power_management": true,
  "show_in_power_info": true,
  "ordered_power_names": [
    "Pets.LightningStorm_Controller.Lightning",
    "Pets.LightningStorm_Controller.Immobilize",
    "Pets.LightningStorm_Controller.Fly"
  ],
  "powers": [
    {
      "name": "Pets.LightningStorm_Controller.Lightning",
      "display_name": "Lightning",
      "icon": "https://reborn-team.github.io/PowersAPI/assets/powers/5a/electricalbolt_lightningbolt.png",
      "display_help": "Sends a large blast of electrical energy at a foe. Electric bolt deals good damage and also drains some Endurance. Note that Lightning is unaffected by Recharge Time changes. Recharge: Fast",
      "display_short_help": "Lightning",
      "display_info": {
        "Recharge Time": "4s",
        "Activation Time": "1.17s",
        "Power Range": "100 ft.",
        "Attack Types": "Ranged, Energy",
        "Available Level": "1",
        "Effect Area": "AoE — 5 ft. radius (5 targets max)",
        "Power Type": "Click",
        "Target Type": "Enemies"
      },
      "attack_types": [
        "Ranged_Def",
        "Energy_Def"
      ],
      "enhancements_allowed": [
        "Enhance Endurance Modification",
        "Enhance Range",
        "Enhance KnockBack",
        "Enhance Damage",
        "Enhance Accuracy"
      ],
      "available_at_level": 1,
      "auto_issue": false,
      "power_type": "Click",
      "accuracy": 1.4,
      "effect_area": {
        "area": "AoE",
        "max_targets_hit": 5,
        "radius_feet": 5.0,
        "range_feet": 100.0
      },
      "target_type_tags": [
        "Foe"
      ],
      "display_target_type": "Enemies",
      "requires_line_of_sight": true,
      "activate": {
        "cast_time": 1.17,
        "animation_time": 1.17,
        "animation_time_before_hit": 0.5,
        "recharge_time": 4.0,
        "endurance_cost": 0.0
      },
      "effect_groups": [
        {
          "visible_in_info_window": true,
          "chance_percent": 100.0,
          "effects": [
            {
              "attributes": [
                "Energy_Dmg"
              ],
              "applies_to": "AbsoluteValue",
              "application_type": "Immediate",
              "target_type": "Affected",
              "magnitude": 1.0,
              "duration": "Instant",
              "flags": [
                "ResistMagnitude",
                "CombatModMagnitude"
              ],
              "stacking": {
                "behavior": "Stack",
                "by_caster": true
              },
              "scaled": [
                {
                  "archetype": "Pet",
                  "damage": 40.04,
                  "average": 40.04,
                  "per_activation": 34.22,
                  "per_cast_cycle": 7.74,
                  "display_info": [
                    "40.04 energy damage on target"
                  ],
                  "base_value": -44.4882,
                  "scale": 0.9
                }
              ]
            },
            {
              "attributes": [
                "Endurance"
              ],
              "applies_to": "CurrentValue",
              "application_type": "Immediate",
              "target_type": "Affected",
              "magnitude": 1.0,
              "duration": "Instant",
              "flags": [
                "ResistMagnitude",
                "CombatModMagnitude"
              ],
              "stacking": {
                "behavior": "Stack",
                "by_caster": true
              },
              "scaled": [
                {
                  "archetype": "Pet",
                  "percent": -7.2,
                  "display_info": [
                    "-7.20% endurance on target"
                  ],
                  "base_value": 1.0,
                  "scale": -0.072
                }
              ]
            },
            {
              "attributes": [
                "Afraid"
              ],
              "applies_to": "CurrentValue",
              "application_type": "OnTick",
              "target_type": "Affected",
              "magnitude": 50.0,
              "duration": "InSecondsScaled",
              "flags": [
                "IgnoreStrength",
                "ResistDuration",
                "CombatModDuration"
              ],
              "stacking": {
                "behavior": "Stack",
                "by_caster": true
              },
              "scaled": [
                {
                  "archetype": "Pet",
                  "duration_seconds": 5.0,
                  "display_info": [
                    "50.0 fear for 5s on target",
                    "Ignores buffs and enhancements"
                  ],
                  "base_value": 1.0,
                  "scale": 5.0
                }
              ]
            }
          ]
        },
        {
          "pve_or_pvp": "PVE",
          "visible_in_info_window": true,
          "chance_percent": 100.0,
          "requires": [
            "target>enttype == critter"
          ],
          "effects": [
            {
              "attributes": [
                "Knockback"
              ],
              "applies_to": "CurrentModifier",
              "application_type": "Immediate",
              "target_type": "Affected",
              "duration": "Instant",
              "flags": [
                "ResistMagnitude",
                "CombatModMagnitude"
              ],
              "stacking": {
                "behavior": "Stack",
                "by_caster": true
              },
              "scaled": [
                {
                  "archetype": "Pet",
                  "magnitude": 1.0,
                  "display_info": [
                    "1.0 magnitude knock on target"
                  ],
                  "base_value": 1.0,
                  "scale": 1.0
                }
              ]
            }
          ]
        },
        {
          "pve_or_pvp": "PVP",
          "visible_in_info_window": true,
          "chance_percent": 100.0,
          "requires": [
            "target>enttype == player"
          ],
          "effects": [
            {
              "attributes": [
                "Knockback"
              ],
              "applies_to": "CurrentModifier",
              "application_type": "Immediate",
              "target_type": "Affected",
              "duration": "Instant",
              "flags": [
                "ResistMagnitude",
                "CombatModMagnitude"
              ],
              "stacking": {
                "behavior": "Stack",
                "by_caster": true
              },
              "scaled": [
                {
                  "archetype": "Pet",
                  "magnitude": 1.0,
                  "display_info": [
                    "1.0 magnitude knock on target"
                  ],
                  "base_value": 1.0,
                  "scale": 1.0
                }
              ]
            }
          ]
        },
        {
          "visible_in_info_window": true,
          "chance_percent": 30.0,
          "effects": [
            {
              "attributes": [
                "Recovery"
              ],
              "applies_to": "CurrentValue",
              "application_type": "OnTick",
              "tick_chance_percent": 100.0,
              "target_type": "Affected",
              "magnitude": 1.0,
              "duration": "InSeconds",
              "duration_seconds": 4.0,
              "flags": [
                "ResistMagnitude",
                "CombatModMagnitude"
              ],
              "stacking": {
                "behavior": "Stack",
                "by_caster": true
              },
              "scaled": [
                {
                  "archetype": "Pet",
                  "percent": -90.0,
                  "display_info": [
                    "-90.00% recovery rate for 4s on target"
                  ],
                  "base_value": 1.0,
                  "scale": -0.9
                }
              ]
            }
          ]
        }
      ]
    },
    {
      "name": "Pets.LightningStorm_Controller.Immobilize",
      "display_name": "Immobilize",
      "icon": "https://reborn-team.github.io/PowersAPI/assets/powers/20/invulnerability_temporaryinvulnerabilty.png",
      "display_help": "All foes that pass near this field will be electrocuted.",
      "display_short_help": "Immobilize",
      "display_info": {
        "Target Type": "Self",
        "Available Level": "1",
        "Effect Area": "Single Target",
        "Power Type": "Auto"
      },
      "available_at_level": 1,
      "auto_issue": false,
      "power_type": "Auto",
      "accuracy": 1.0,
      "effect_area": {
        "area": "SingleTarget"
      },
      "target_type_tags": [
        "Self",
        "Alive",
        "Dead"
      ],
      "display_target_type": "Self",
      "target_auto_hit_tags": [
        [
          "Self",
          "Alive",
          "Dead"
        ]
      ],
      "display_target_auto_hit": [
        "Self"
      ],
      "requires_line_of_sight": true,
      "activate": {
        "cast_time": 0.0,
        "animation_time": 1.17,
        "animation_time_before_hit": 0.5,
        "recharge_time": 0.0,
        "auto_cast_interval": 0.2,
        "endurance_cost": 0.0
      },
      "effect_groups": [
        {
          "visible_in_info_window": true,
          "chance_percent": 100.0,
          "effects": [
            {
              "attributes": [
                "Translucency"
              ],
              "applies_to": "Special",
              "application_type": "OnTick",
              "tick_chance_percent": 100.0,
              "target_type": "Self",
              "duration": "InSeconds",
              "duration_seconds": 0.5,
              "flags": [
                "IgnoreStrength",
                "ResistMagnitude",
                "CombatModMagnitude"
              ],
              "stacking": {
                "behavior": "Replace",
                "by_caster": true
              }
            },
            {
              "attributes": [
                "Immobilized"
              ],
              "applies_to": "CurrentModifier",
              "application_type": "OnTick",
              "target_type": "Self",
              "magnitude": 100.0,
              "duration": "InSecondsScaled",
              "flags": [
                "IgnoreStrength",
                "IgnoreResistance",
                "CombatModDuration"
              ],
              "stacking": {
                "behavior": "Replace",
                "by_caster": true
              },
              "scaled": [
                {
                  "archetype": "Pet",
                  "duration_seconds": 0.45,
                  "display_info": [
                    "100.0 immobilize for 0.45s on self",
                    "Ignores buffs and enhancements",
                    "Unresistable"
                  ],
                  "base_value": 1.0,
                  "scale": 0.45
                }
              ]
            },
            {
              "attributes": [
                "Healing_Dmg"
              ],
              "applies_to": "Resistance",
              "application_type": "OnTick",
              "tick_chance_percent": 100.0,
              "target_type": "Self",
              "magnitude": 1.0,
              "duration": "InSeconds",
              "duration_seconds": 0.5,
              "flags": [
                "IgnoreStrength",
                "IgnoreResistance",
                "CombatModMagnitude"
              ],
              "stacking": {
                "behavior": "Replace",
                "by_caster": true
              },
              "scaled": [
                {
                  "archetype": "Pet",
                  "percent": 10000.0,
                  "display_info": [
                    "10000.00% resistance to healing for 0.5s on self",
                    "Ignores buffs and enhancements",
                    "Unresistable"
                  ],
                  "base_value": 1.0,
                  "scale": 100.0
                }
              ]
            }
          ]
        }
      ]
    },
    {
      "name": "Pets.LightningStorm_Controller.Fly",
      "display_name": "Fly",
      "icon": "https://reborn-team.github.io/PowersAPI/assets/powers/7c/flight_travelflight.png",
      "display_help": "Lightning Storm can Hover.",
      "display_short_help": "Self Hover",
      "display_info": {
        "Target Type": "Self",
        "Power Type": "Auto",
        "Effect Area": "Single Target",
        "Available Level": "1"
      },
      "available_at_level": 1,
      "auto_issue": false,
      "power_type": "Auto",
      "accuracy": 1.0,
      "effect_area": {
        "area": "SingleTarget"
      },
      "target_type_tags": [
        "Self",
        "Alive",
        "Dead"
      ],
      "display_target_type": "Self",
      "target_auto_hit_tags": [
        [
          "Self",
          "Alive",
          "Dead"
        ]
      ],
      "display_target_auto_hit": [
        "Self"
      ],
      "requires_line_of_sight": true,
      "activate": {
        "cast_time": 0.0,
        "animation_time": 1.17,
        "animation_time_before_hit": 0.5,
        "recharge_time": 0.0,
        "auto_cast_interval": 5.0,
        "endurance_cost": 0.0
      },
      "effect_groups": [
        {
          "visible_in_info_window": true,
          "chance_percent": 100.0,
          "effects": [
            {
              "attributes": [
                "Fly"
              ],
              "applies_to": "CurrentValue",
              "application_type": "OnTick",
              "tick_chance_percent": 100.0,
              "target_type": "Self",
              "duration": "InSeconds",
              "duration_seconds": 5.25,
              "flags": [
                "IgnoreResistance",
                "CombatModMagnitude"
              ],
              "stacking": {
                "behavior": "Replace",
                "by_caster": true
              },
              "scaled": [
                {
                  "archetype": "Pet",
                  "magnitude": 100.0,
                  "display_info": [
                    "100.0 magnitude fly for 5.25s on self",
                    "Unresistable"
                  ],
                  "base_value": 1.0,
                  "scale": 100.0
                }
              ]
            }
          ]
        }
      ]
    }
  ]
}