{
  "issue": "i26p5",
  "source": "homecoming",
  "extract_date": "2020-08-11T21:52:57.192132400-07:00",
  "name": "Widow_Training.Widow_Training",
  "display_name": "Widow Training",
  "display_help": "Characters with Widow Training begin their careers as Blood Widows. Blood Widow characters begin with modest melee, ranged and buff skills. Beginning at level 24, they may chose to switch to the \"Fortunata\" path or remain on the \"Widow\" path and become \"Night Widows.\" Night Widows gain considerably stronger melee capabilities, and only have modest ranged abilities, while those who go with the Fortunata path learn stronger ranged attack abilities and control abilities.",
  "icon": "https://reborn-team.github.io/PowersAPI/assets/powers/7d/widowtraining_poisondart.png",
  "show_in_inventory": "Show",
  "show_in_power_management": true,
  "show_in_power_info": true,
  "ordered_power_names": [
    "Widow_Training.Widow_Training.Poison_Dart",
    "Widow_Training.Widow_Training.Swipe",
    "Widow_Training.Widow_Training.Lunge",
    "Widow_Training.Widow_Training.Dart_Burst",
    "Widow_Training.Widow_Training.Follow_Up",
    "Widow_Training.Widow_Training.Spin",
    "Widow_Training.Widow_Training.Strike",
    "Widow_Training.Widow_Training.Confront"
  ],
  "powers": [
    {
      "name": "Widow_Training.Widow_Training.Poison_Dart",
      "display_name": "Poison Dart",
      "icon": "https://reborn-team.github.io/PowersAPI/assets/powers/7d/widowtraining_poisondart.png",
      "display_help": "Poison Dart does moderate damage to your foe, then poisons them. The poison does toxic damage over time and reduces their regeneration rate. Damage: Moderate, Recharge: Fast",
      "display_short_help": "Moderate DMG (Lethal), DoT(Toxic), -Regeneration",
      "display_info": {
        "Recharge Time": "4s",
        "Endurance Cost": "5.20",
        "Activation Time": "1.5s",
        "Power Type": "Click",
        "Power Range": "80 ft.",
        "Effect Area": "Single Target",
        "Attack Types": "Ranged, Lethal",
        "Available Level": "1",
        "Target Type": "Enemies"
      },
      "attack_types": [
        "Ranged_Def",
        "Lethal_Def"
      ],
      "enhancements_allowed": [
        "Reduce Endurance Cost",
        "Enhance Range",
        "Enhance Recharge Speed",
        "Enhance Damage",
        "Enhance Accuracy"
      ],
      "enhancement_set_categories_allowed": [
        "Soldiers of Arachnos Archetype Sets",
        "Ranged Damage",
        "Universal Damage Sets"
      ],
      "available_at_level": 1,
      "auto_issue": false,
      "power_type": "Click",
      "accuracy": 1.05,
      "effect_area": {
        "area": "SingleTarget",
        "range_feet": 80.0
      },
      "target_type_tags": [
        "Foe"
      ],
      "display_target_type": "Enemies",
      "requires_line_of_sight": true,
      "modes_disallowed": [
        "Disable_All"
      ],
      "activate": {
        "cast_time": 1.5,
        "animation_time": 1.5,
        "animation_time_before_hit": 1.0,
        "recharge_time": 4.0,
        "endurance_cost": 5.2
      },
      "effect_groups": [
        {
          "pve_or_pvp": "PVE",
          "visible_in_info_window": true,
          "chance_percent": 100.0,
          "requires": [
            "target>enttype == critter"
          ],
          "effects": [
            {
              "attributes": [
                "Lethal_Dmg"
              ],
              "applies_to": "AbsoluteValue",
              "application_type": "Immediate",
              "target_type": "Affected",
              "magnitude": 1.0,
              "duration": "Instant",
              "flags": [
                "ResistMagnitude",
                "CombatModMagnitude"
              ],
              "stacking": {
                "behavior": "Stack",
                "by_caster": true
              },
              "scaled": [
                {
                  "archetype": "Arachnos Widow",
                  "damage": 55.61,
                  "average": 55.61,
                  "per_activation": 37.07,
                  "per_cast_cycle": 10.11,
                  "display_info": [
                    "55.61 lethal damage on target"
                  ],
                  "base_value": -55.6102,
                  "scale": 1.0
                }
              ]
            }
          ]
        },
        {
          "visible_in_info_window": true,
          "chance_percent": 100.0,
          "effects": [
            {
              "attributes": [
                "Regeneration"
              ],
              "applies_to": "CurrentValue",
              "application_type": "OnTick",
              "tick_chance_percent": 100.0,
              "target_type": "Affected",
              "magnitude": 1.0,
              "duration": "InSeconds",
              "duration_seconds": 15.0,
              "flags": [
                "ResistMagnitude",
                "CombatModMagnitude"
              ],
              "stacking": {
                "behavior": "Stack",
                "by_caster": true
              },
              "scaled": [
                {
                  "archetype": "Arachnos Widow",
                  "percent": -25.0,
                  "display_info": [
                    "-25.00% regeneration rate for 15s on target"
                  ],
                  "base_value": 1.0,
                  "scale": -0.25
                }
              ]
            },
            {
              "attributes": [
                "Toxic_Dmg"
              ],
              "applies_to": "AbsoluteValue",
              "application_type": "OnTick",
              "tick_chance_percent": 100.0,
              "target_type": "Affected",
              "magnitude": 1.0,
              "duration": "InSeconds",
              "duration_seconds": 2.1,
              "continuous_apply_seconds": 1.0,
              "ticks": 3,
              "flags": [
                "CancelOnMiss",
                "ResistMagnitude",
                "CombatModMagnitude"
              ],
              "stacking": {
                "behavior": "Stack",
                "by_caster": true
              },
              "scaled": [
                {
                  "archetype": "Arachnos Widow",
                  "damage": 5.56,
                  "average": 5.56,
                  "per_activation": 3.71,
                  "per_cast_cycle": 1.01,
                  "display_info": [
                    "3 ticks of 5.56 toxic damage over 2.1s on target"
                  ],
                  "base_value": -55.6102,
                  "scale": 0.1
                }
              ]
            }
          ]
        },
        {
          "pve_or_pvp": "PVP",
          "visible_in_info_window": true,
          "chance_percent": 100.0,
          "requires": [
            "target>enttype == player"
          ],
          "effects": [
            {
              "attributes": [
                "Lethal_Dmg"
              ],
              "applies_to": "AbsoluteValue",
              "application_type": "Immediate",
              "target_type": "Affected",
              "magnitude": 1.0,
              "duration": "Instant",
              "flags": [
                "ResistMagnitude",
                "CombatModMagnitude"
              ],
              "stacking": {
                "behavior": "Stack",
                "by_caster": true
              },
              "scaled": [
                {
                  "archetype": "Arachnos Widow",
                  "damage": 90.82,
                  "average": 90.82,
                  "per_activation": 60.55,
                  "per_cast_cycle": 16.51,
                  "display_info": [
                    "90.82 lethal damage on target"
                  ],
                  "base_value": -56.4132,
                  "scale": 1.6099
                }
              ]
            }
          ]
        }
      ]
    },
    {
      "name": "Widow_Training.Widow_Training.Swipe",
      "display_name": "Swipe",
      "icon": "https://reborn-team.github.io/PowersAPI/assets/powers/95/widowtraining_swipe.png",
      "display_help": "Swipe does light lethal damage to your foe, then poisons them. The poison does toxic damage over time and slows their recovery rate and movement speed. NOTE: This power will deal critical damage if used after a successful Placate or while the user is hidden with the Night Widow or Fortunata Mask Presence power. Damage: Light, Recharge: Fast",
      "display_short_help": "Light DMG (Lethal), DoT(Toxic), -Recharge, -SPD",
      "display_info": {
        "Effect Area": "Single Target",
        "Recharge Time": "4s",
        "Power Type": "Click",
        "Activation Time": "0.83s",
        "Endurance Cost": "4.16",
        "Power Range": "7 ft.",
        "Attack Types": "Melee, Lethal",
        "Available Level": "1",
        "Target Type": "Enemies"
      },
      "attack_types": [
        "Melee_Def",
        "Lethal_Def"
      ],
      "enhancements_allowed": [
        "Reduce Endurance Cost",
        "Enhance Recharge Speed",
        "Enhance Damage",
        "Enhance Accuracy"
      ],
      "enhancement_set_categories_allowed": [
        "Melee Damage",
        "Soldiers of Arachnos Archetype Sets",
        "Universal Damage Sets"
      ],
      "available_at_level": 1,
      "auto_issue": false,
      "power_type": "Click",
      "accuracy": 1.0,
      "effect_area": {
        "area": "SingleTarget",
        "range_feet": 7.0
      },
      "target_type_tags": [
        "Foe"
      ],
      "display_target_type": "Enemies",
      "requires_line_of_sight": true,
      "modes_disallowed": [
        "Disable_All"
      ],
      "activate": {
        "cast_time": 0.83,
        "animation_time": 0.83,
        "animation_time_before_hit": 0.5,
        "recharge_time": 4.0,
        "endurance_cost": 4.16
      },
      "effect_groups": [
        {
          "pve_or_pvp": "PVE",
          "visible_in_info_window": true,
          "chance_percent": 100.0,
          "requires": [
            "target>enttype == critter"
          ],
          "effects": [
            {
              "attributes": [
                "Lethal_Dmg"
              ],
              "applies_to": "AbsoluteValue",
              "application_type": "Immediate",
              "target_type": "Affected",
              "magnitude": 1.0,
              "duration": "Instant",
              "flags": [
                "ResistMagnitude",
                "CombatModMagnitude"
              ],
              "stacking": {
                "behavior": "Stack",
                "by_caster": true
              },
              "scaled": [
                {
                  "archetype": "Arachnos Widow",
                  "damage": 44.49,
                  "average": 44.49,
                  "per_activation": 53.6,
                  "per_cast_cycle": 9.21,
                  "display_info": [
                    "44.49 lethal damage on target"
                  ],
                  "base_value": -55.6102,
                  "scale": 0.8
                }
              ]
            }
          ]
        },
        {
          "pve_or_pvp": "PVE",
          "visible_in_info_window": true,
          "chance_percent": 100.0,
          "requires": [
            "(source>kMeter > 0) && (target>enttype == critter)"
          ],
          "effects": [
            {
              "attributes": [
                "Lethal_Dmg"
              ],
              "applies_to": "AbsoluteValue",
              "application_type": "Immediate",
              "target_type": "Affected",
              "magnitude": 1.0,
              "duration": "Instant",
              "flags": [
                "ResistMagnitude",
                "CombatModMagnitude"
              ],
              "stacking": {
                "behavior": "Stack",
                "by_caster": true
              },
              "scaled": [
                {
                  "archetype": "Arachnos Widow",
                  "damage": 29.66,
                  "average": 29.66,
                  "per_activation": 35.73,
                  "per_cast_cycle": 6.14,
                  "display_info": [
                    "29.66 lethal damage on target",
                    "Only if hidden or target placated"
                  ],
                  "base_value": -55.6102,
                  "scale": 0.5333
                }
              ]
            }
          ]
        },
        {
          "pve_or_pvp": "PVP",
          "visible_in_info_window": true,
          "chance_percent": 100.0,
          "requires": [
            "target>enttype == player"
          ],
          "effects": [
            {
              "attributes": [
                "Lethal_Dmg"
              ],
              "applies_to": "AbsoluteValue",
              "application_type": "Immediate",
              "target_type": "Affected",
              "magnitude": 1.0,
              "duration": "Instant",
              "flags": [
                "ResistMagnitude",
                "CombatModMagnitude"
              ],
              "stacking": {
                "behavior": "Stack",
                "by_caster": true
              },
              "scaled": [
                {
                  "archetype": "Arachnos Widow",
                  "damage": 64.37,
                  "average": 64.37,
                  "per_activation": 77.55,
                  "per_cast_cycle": 13.33,
                  "display_info": [
                    "64.37 lethal damage on target"
                  ],
                  "base_value": -56.4121,
                  "scale": 1.141
                }
              ]
            }
          ]
        },
        {
          "pve_or_pvp": "PVP",
          "visible_in_info_window": true,
          "chance_percent": 100.0,
          "requires": [
            "(source>kMeter > 0) && (target>enttype == player)"
          ],
          "effects": [
            {
              "attributes": [
                "Lethal_Dmg"
              ],
              "applies_to": "AbsoluteValue",
              "application_type": "Immediate",
              "target_type": "Affected",
              "magnitude": 1.0,
              "duration": "Instant",
              "flags": [
                "ResistMagnitude",
                "CombatModMagnitude"
              ],
              "stacking": {
                "behavior": "Stack",
                "by_caster": true
              },
              "scaled": [
                {
                  "archetype": "Arachnos Widow",
                  "damage": 42.93,
                  "average": 42.93,
                  "per_activation": 51.72,
                  "per_cast_cycle": 8.89,
                  "display_info": [
                    "42.93 lethal damage on target",
                    "Only if hidden or target placated"
                  ],
                  "base_value": -56.4121,
                  "scale": 0.761
                }
              ]
            }
          ]
        },
        {
          "visible_in_info_window": true,
          "chance_percent": 100.0,
          "effects": [
            {
              "attributes": [
                "RunningSpeed",
                "FlyingSpeed",
                "JumpingSpeed"
              ],
              "applies_to": "CurrentValue",
              "application_type": "OnTick",
              "tick_chance_percent": 100.0,
              "target_type": "Affected",
              "magnitude": 1.0,
              "duration": "InSeconds",
              "duration_seconds": 4.0,
              "flags": [
                "ResistMagnitude",
                "CombatModMagnitude"
              ],
              "stacking": {
                "behavior": "Stack",
                "by_caster": true
              },
              "scaled": [
                {
                  "archetype": "Arachnos Widow",
                  "percent": -20.0,
                  "display_info": [
                    "-20.00% run speed, fly speed, jump speed for 4s on target"
                  ],
                  "base_value": -1.0,
                  "scale": 0.2
                }
              ]
            },
            {
              "attributes": [
                "JumpHeight",
                "RechargeTime"
              ],
              "applies_to": "Strength",
              "application_type": "OnTick",
              "tick_chance_percent": 100.0,
              "target_type": "Affected",
              "magnitude": 1.0,
              "duration": "InSeconds",
              "duration_seconds": 4.0,
              "flags": [
                "IgnoreStrength",
                "ResistMagnitude",
                "CombatModMagnitude"
              ],
              "stacking": {
                "behavior": "Stack",
                "by_caster": true
              },
              "scaled": [
                {
                  "archetype": "Arachnos Widow",
                  "percent": -20.0,
                  "display_info": [
                    "-20.00% strength to jump height, recharge for 4s on target",
                    "Ignores buffs and enhancements"
                  ],
                  "base_value": -1.0,
                  "scale": 0.2
                }
              ]
            },
            {
              "attributes": [
                "Toxic_Dmg"
              ],
              "applies_to": "AbsoluteValue",
              "application_type": "OnTick",
              "tick_chance_percent": 100.0,
              "target_type": "Affected",
              "magnitude": 1.0,
              "duration": "InSeconds",
              "duration_seconds": 2.1,
              "after_delay_seconds": 0.5,
              "continuous_apply_seconds": 1.0,
              "ticks": 3,
              "flags": [
                "CancelOnMiss",
                "ResistMagnitude",
                "CombatModMagnitude"
              ],
              "stacking": {
                "behavior": "Stack",
                "by_caster": true
              },
              "scaled": [
                {
                  "archetype": "Arachnos Widow",
                  "damage": 4.45,
                  "average": 4.45,
                  "per_activation": 5.36,
                  "per_cast_cycle": 0.92,
                  "display_info": [
                    "3 ticks of 4.45 toxic damage over 2.1s on target after 0.5s delay"
                  ],
                  "base_value": -55.6102,
                  "scale": 0.08
                }
              ]
            }
          ]
        }
      ]
    },
    {
      "name": "Widow_Training.Widow_Training.Lunge",
      "display_name": "Strike",
      "icon": "https://reborn-team.github.io/PowersAPI/assets/powers/56/widowtraining_strike.png",
      "display_help": "Strike does high lethal damage to your foe, then poisons them. The poison does toxic damage over time and slows their recovery rate and movement speed. NOTE: This power will deal critical damage if used after a successful Placate or while the user is hidden with the Night Widow or Fortunata Mask Presence power. Damage: High, Recharge: Moderate",
      "display_short_help": "High DMG (Lethal), DoT(Toxic), -Recharge, -SPD",
      "display_info": {
        "Power Type": "Click",
        "Endurance Cost": "7.47",
        "Recharge Time": "8s",
        "Available Level": "2",
        "Effect Area": "Single Target",
        "Attack Types": "Melee, Lethal",
        "Target Type": "Enemies",
        "Activation Time": "1.17s",
        "Power Range": "7 ft."
      },
      "attack_types": [
        "Melee_Def",
        "Lethal_Def"
      ],
      "enhancements_allowed": [
        "Reduce Endurance Cost",
        "Enhance Recharge Speed",
        "Enhance Damage",
        "Enhance Accuracy"
      ],
      "enhancement_set_categories_allowed": [
        "Soldiers of Arachnos Archetype Sets",
        "Universal Damage Sets",
        "Melee Damage"
      ],
      "available_at_level": 2,
      "auto_issue": false,
      "power_type": "Click",
      "accuracy": 1.0,
      "effect_area": {
        "area": "SingleTarget",
        "range_feet": 7.0
      },
      "target_type_tags": [
        "Foe"
      ],
      "display_target_type": "Enemies",
      "requires_line_of_sight": true,
      "modes_disallowed": [
        "Disable_All"
      ],
      "activate": {
        "cast_time": 1.17,
        "animation_time": 1.17,
        "animation_time_before_hit": 0.5,
        "recharge_time": 8.0,
        "endurance_cost": 7.47
      },
      "effect_groups": [
        {
          "pve_or_pvp": "PVE",
          "visible_in_info_window": true,
          "chance_percent": 100.0,
          "requires": [
            "target>enttype == critter"
          ],
          "effects": [
            {
              "attributes": [
                "Lethal_Dmg"
              ],
              "applies_to": "AbsoluteValue",
              "application_type": "Immediate",
              "target_type": "Affected",
              "magnitude": 1.0,
              "duration": "Instant",
              "flags": [
                "ResistMagnitude",
                "CombatModMagnitude"
              ],
              "stacking": {
                "behavior": "Stack",
                "by_caster": true
              },
              "scaled": [
                {
                  "archetype": "Arachnos Widow",
                  "damage": 79.93,
                  "average": 79.93,
                  "per_activation": 68.32,
                  "per_cast_cycle": 8.72,
                  "display_info": [
                    "79.93 lethal damage on target"
                  ],
                  "base_value": -55.6102,
                  "scale": 1.4373
                }
              ]
            }
          ]
        },
        {
          "pve_or_pvp": "PVE",
          "visible_in_info_window": true,
          "chance_percent": 100.0,
          "requires": [
            "(source>kMeter > 0) && (target>enttype == critter)"
          ],
          "effects": [
            {
              "attributes": [
                "Lethal_Dmg"
              ],
              "applies_to": "AbsoluteValue",
              "application_type": "Immediate",
              "target_type": "Affected",
              "magnitude": 1.0,
              "duration": "Instant",
              "flags": [
                "ResistMagnitude",
                "CombatModMagnitude"
              ],
              "stacking": {
                "behavior": "Stack",
                "by_caster": true
              },
              "scaled": [
                {
                  "archetype": "Arachnos Widow",
                  "damage": 53.29,
                  "average": 53.29,
                  "per_activation": 45.55,
                  "per_cast_cycle": 5.81,
                  "display_info": [
                    "53.29 lethal damage on target",
                    "Only if hidden or target placated"
                  ],
                  "base_value": -55.6102,
                  "scale": 0.9582
                }
              ]
            }
          ]
        },
        {
          "pve_or_pvp": "PVP",
          "visible_in_info_window": true,
          "chance_percent": 100.0,
          "requires": [
            "target>enttype == player"
          ],
          "effects": [
            {
              "attributes": [
                "Lethal_Dmg"
              ],
              "applies_to": "AbsoluteValue",
              "application_type": "Immediate",
              "target_type": "Affected",
              "magnitude": 1.0,
              "duration": "Instant",
              "flags": [
                "ResistMagnitude",
                "CombatModMagnitude"
              ],
              "stacking": {
                "behavior": "Stack",
                "by_caster": true
              },
              "scaled": [
                {
                  "archetype": "Arachnos Widow",
                  "damage": 86.82,
                  "average": 86.82,
                  "per_activation": 74.21,
                  "per_cast_cycle": 9.47,
                  "display_info": [
                    "86.82 lethal damage on target"
                  ],
                  "base_value": -56.4121,
                  "scale": 1.539
                }
              ]
            }
          ]
        },
        {
          "pve_or_pvp": "PVP",
          "visible_in_info_window": true,
          "chance_percent": 100.0,
          "requires": [
            "(source>kMeter > 0) && (target>enttype == player)"
          ],
          "effects": [
            {
              "attributes": [
                "Lethal_Dmg"
              ],
              "applies_to": "AbsoluteValue",
              "application_type": "Immediate",
              "target_type": "Affected",
              "magnitude": 1.0,
              "duration": "Instant",
              "flags": [
                "ResistMagnitude",
                "CombatModMagnitude"
              ],
              "stacking": {
                "behavior": "Stack",
                "by_caster": true
              },
              "scaled": [
                {
                  "archetype": "Arachnos Widow",
                  "damage": 57.91,
                  "average": 57.91,
                  "per_activation": 49.5,
                  "per_cast_cycle": 6.32,
                  "display_info": [
                    "57.91 lethal damage on target",
                    "Only if hidden or target placated"
                  ],
                  "base_value": -56.4121,
                  "scale": 1.0265
                }
              ]
            }
          ]
        },
        {
          "visible_in_info_window": true,
          "chance_percent": 100.0,
          "effects": [
            {
              "attributes": [
                "RunningSpeed",
                "FlyingSpeed",
                "JumpingSpeed"
              ],
              "applies_to": "CurrentValue",
              "application_type": "OnTick",
              "tick_chance_percent": 100.0,
              "target_type": "Affected",
              "magnitude": 1.0,
              "duration": "InSeconds",
              "duration_seconds": 6.0,
              "flags": [
                "ResistMagnitude",
                "CombatModMagnitude"
              ],
              "stacking": {
                "behavior": "Stack",
                "by_caster": true
              },
              "scaled": [
                {
                  "archetype": "Arachnos Widow",
                  "percent": -20.0,
                  "display_info": [
                    "-20.00% run speed, fly speed, jump speed for 6s on target"
                  ],
                  "base_value": -1.0,
                  "scale": 0.2
                }
              ]
            },
            {
              "attributes": [
                "JumpHeight",
                "RechargeTime"
              ],
              "applies_to": "Strength",
              "application_type": "OnTick",
              "tick_chance_percent": 100.0,
              "target_type": "Affected",
              "magnitude": 1.0,
              "duration": "InSeconds",
              "duration_seconds": 6.0,
              "flags": [
                "IgnoreStrength",
                "ResistMagnitude",
                "CombatModMagnitude"
              ],
              "stacking": {
                "behavior": "Stack",
                "by_caster": true
              },
              "scaled": [
                {
                  "archetype": "Arachnos Widow",
                  "percent": -20.0,
                  "display_info": [
                    "-20.00% strength to jump height, recharge for 6s on target",
                    "Ignores buffs and enhancements"
                  ],
                  "base_value": -1.0,
                  "scale": 0.2
                }
              ]
            },
            {
              "attributes": [
                "Toxic_Dmg"
              ],
              "applies_to": "AbsoluteValue",
              "application_type": "OnTick",
              "tick_chance_percent": 100.0,
              "target_type": "Affected",
              "magnitude": 1.0,
              "duration": "InSeconds",
              "duration_seconds": 3.1,
              "after_delay_seconds": 0.5,
              "continuous_apply_seconds": 1.0,
              "ticks": 4,
              "flags": [
                "CancelOnMiss",
                "ResistMagnitude",
                "CombatModMagnitude"
              ],
              "stacking": {
                "behavior": "Stack",
                "by_caster": true
              },
              "scaled": [
                {
                  "archetype": "Arachnos Widow",
                  "damage": 3.89,
                  "average": 3.89,
                  "per_activation": 3.32,
                  "per_cast_cycle": 0.42,
                  "display_info": [
                    "4 ticks of 3.89 toxic damage over 3.1s on target after 0.5s delay"
                  ],
                  "base_value": -55.6102,
                  "scale": 0.07
                }
              ]
            }
          ]
        }
      ]
    },
    {
      "name": "Widow_Training.Widow_Training.Dart_Burst",
      "display_name": "Dart Burst",
      "icon": "https://reborn-team.github.io/PowersAPI/assets/powers/b9/widowtraining_dartburst.png",
      "display_help": "Dart Burst does light lethal damage to foes in a 30 degree arc cone, then poisons them. The poison does toxic damage over time and reduces their regeneration rate. Damage: Light, Recharge: Moderate",
      "display_short_help": "Light Cone DMG (Lethal), DoT(Toxic), -Regeneration",
      "display_info": {
        "Recharge Time": "8s",
        "Available Level": "6",
        "Activation Time": "2s",
        "Attack Types": "Ranged, Lethal",
        "Effect Area": "Cone — 50 ft. radius 30° arc (10 targets max)",
        "Endurance Cost": "8.53",
        "Target Type": "Enemies",
        "Power Range": "50 ft.",
        "Power Type": "Click"
      },
      "attack_types": [
        "Ranged_Def",
        "Lethal_Def"
      ],
      "enhancements_allowed": [
        "Reduce Endurance Cost",
        "Enhance Range",
        "Enhance Recharge Speed",
        "Enhance Damage",
        "Enhance Accuracy"
      ],
      "enhancement_set_categories_allowed": [
        "Universal Damage Sets",
        "Targeted AoE Damage",
        "Soldiers of Arachnos Archetype Sets"
      ],
      "available_at_level": 6,
      "auto_issue": false,
      "power_type": "Click",
      "accuracy": 1.05,
      "effect_area": {
        "area": "Cone",
        "max_targets_hit": 10,
        "radius_feet": 50.0,
        "arc_degrees": 30.0,
        "range_feet": 50.0
      },
      "target_type_tags": [
        "Foe"
      ],
      "display_target_type": "Enemies",
      "requires_line_of_sight": true,
      "modes_disallowed": [
        "Disable_All"
      ],
      "activate": {
        "cast_time": 2.0,
        "animation_time": 2.0,
        "animation_time_before_hit": 0.87,
        "recharge_time": 8.0,
        "endurance_cost": 8.53
      },
      "effect_groups": [
        {
          "pve_or_pvp": "PVE",
          "visible_in_info_window": true,
          "chance_percent": 100.0,
          "requires": [
            "target>enttype == critter"
          ],
          "effects": [
            {
              "attributes": [
                "Lethal_Dmg"
              ],
              "applies_to": "AbsoluteValue",
              "application_type": "OnTick",
              "tick_chance_percent": 100.0,
              "target_type": "Affected",
              "magnitude": 1.0,
              "duration": "InSeconds",
              "duration_seconds": 0.8,
              "continuous_apply_seconds": 0.33,
              "ticks": 3,
              "flags": [
                "ResistMagnitude",
                "CombatModMagnitude"
              ],
              "stacking": {
                "behavior": "Stack",
                "by_caster": true
              },
              "scaled": [
                {
                  "archetype": "Arachnos Widow",
                  "damage": 14.18,
                  "average": 14.18,
                  "per_activation": 7.09,
                  "per_cast_cycle": 1.42,
                  "display_info": [
                    "3 ticks of 14.18 lethal damage over 0.8s on target"
                  ],
                  "base_value": -55.6102,
                  "scale": 0.255
                }
              ]
            }
          ]
        },
        {
          "visible_in_info_window": true,
          "chance_percent": 100.0,
          "effects": [
            {
              "attributes": [
                "Regeneration"
              ],
              "applies_to": "CurrentValue",
              "application_type": "OnTick",
              "tick_chance_percent": 100.0,
              "target_type": "Affected",
              "magnitude": 1.0,
              "duration": "InSeconds",
              "duration_seconds": 15.0,
              "flags": [
                "ResistMagnitude",
                "CombatModMagnitude"
              ],
              "stacking": {
                "behavior": "Stack",
                "by_caster": true
              },
              "scaled": [
                {
                  "archetype": "Arachnos Widow",
                  "percent": -25.0,
                  "display_info": [
                    "-25.00% regeneration rate for 15s on target"
                  ],
                  "base_value": 1.0,
                  "scale": -0.25
                }
              ]
            },
            {
              "attributes": [
                "Toxic_Dmg"
              ],
              "applies_to": "AbsoluteValue",
              "application_type": "OnTick",
              "tick_chance_percent": 80.0,
              "target_type": "Affected",
              "magnitude": 1.0,
              "duration": "InSeconds",
              "duration_seconds": 5.0,
              "continuous_apply_seconds": 1.0,
              "ticks": 6,
              "flags": [
                "CancelOnMiss",
                "ResistMagnitude",
                "CombatModMagnitude"
              ],
              "stacking": {
                "behavior": "Stack",
                "by_caster": true
              },
              "scaled": [
                {
                  "archetype": "Arachnos Widow",
                  "damage": 6.12,
                  "average": 18.06,
                  "per_activation": 9.03,
                  "per_cast_cycle": 1.81,
                  "display_info": [
                    "6 ticks of 80.00% chance for 6.12 toxic damage over 5s on target"
                  ],
                  "base_value": -55.6102,
                  "scale": 0.11
                }
              ]
            }
          ]
        },
        {
          "pve_or_pvp": "PVP",
          "visible_in_info_window": true,
          "chance_percent": 100.0,
          "requires": [
            "target>enttype == player"
          ],
          "effects": [
            {
              "attributes": [
                "Lethal_Dmg"
              ],
              "applies_to": "AbsoluteValue",
              "application_type": "Immediate",
              "target_type": "Affected",
              "magnitude": 1.0,
              "duration": "Instant",
              "flags": [
                "ResistMagnitude",
                "CombatModMagnitude"
              ],
              "stacking": {
                "behavior": "Stack",
                "by_caster": true
              },
              "scaled": [
                {
                  "archetype": "Arachnos Widow",
                  "damage": 48.81,
                  "average": 48.81,
                  "per_activation": 24.41,
                  "per_cast_cycle": 4.88,
                  "display_info": [
                    "48.81 lethal damage on target"
                  ],
                  "base_value": -56.4132,
                  "scale": 0.8653
                }
              ]
            }
          ]
        }
      ]
    },
    {
      "name": "Widow_Training.Widow_Training.Follow_Up",
      "display_name": "Follow Up",
      "icon": "https://reborn-team.github.io/PowersAPI/assets/powers/d1/widowtraining_followup.png",
      "display_help": "You perform a feint attack that deals moderate damage. After this attack hits, it gives you a large bonus to your chance to hit and damage for a brief time. NOTE: This power will deal critical damage if used after a successful Placate or while the user is hidden with the Night Widow or Fortunata Mask Presence power, additionally if you select this power, you may not also select Build Up. Damage: Moderate, Recharge: Slow",
      "display_short_help": "Melee, Moderate DMG(Lethal), Self +DMG",
      "display_info": {
        "Effect Area": "Single Target",
        "Recharge Time": "12s",
        "Attack Types": "Melee, Lethal",
        "Available Level": "8",
        "Power Range": "7 ft.",
        "Endurance Cost": "7.80",
        "Activation Time": "0.83s",
        "Power Type": "Click",
        "Target Type": "Enemies"
      },
      "requires": "!Widow_Training.Night_Widow_Training.Build_Up",
      "attack_types": [
        "Melee_Def",
        "Lethal_Def"
      ],
      "enhancements_allowed": [
        "Reduce Endurance Cost",
        "Enhance Recharge Speed",
        "Enhance Damage",
        "Enhance ToHit Buffs",
        "Enhance Accuracy"
      ],
      "enhancement_set_categories_allowed": [
        "Melee Damage",
        "Soldiers of Arachnos Archetype Sets",
        "To Hit Buff",
        "Universal Damage Sets"
      ],
      "available_at_level": 8,
      "auto_issue": false,
      "power_type": "Click",
      "accuracy": 1.0,
      "effect_area": {
        "area": "SingleTarget",
        "range_feet": 7.0
      },
      "target_type_tags": [
        "Foe"
      ],
      "display_target_type": "Enemies",
      "requires_line_of_sight": true,
      "modes_disallowed": [
        "Disable_All"
      ],
      "activate": {
        "cast_time": 0.83,
        "animation_time": 0.83,
        "animation_time_before_hit": 0.5,
        "recharge_time": 12.0,
        "endurance_cost": 7.8
      },
      "effect_groups": [
        {
          "pve_or_pvp": "PVE",
          "visible_in_info_window": true,
          "chance_percent": 100.0,
          "requires": [
            "target>enttype == critter"
          ],
          "effects": [
            {
              "attributes": [
                "Lethal_Dmg"
              ],
              "applies_to": "AbsoluteValue",
              "application_type": "Immediate",
              "target_type": "Affected",
              "magnitude": 1.0,
              "duration": "Instant",
              "flags": [
                "ResistMagnitude",
                "CombatModMagnitude"
              ],
              "stacking": {
                "behavior": "Stack",
                "by_caster": true
              },
              "scaled": [
                {
                  "archetype": "Arachnos Widow",
                  "damage": 50.72,
                  "average": 50.72,
                  "per_activation": 61.11,
                  "per_cast_cycle": 3.95,
                  "display_info": [
                    "50.72 lethal damage on target"
                  ],
                  "base_value": -55.6102,
                  "scale": 0.912
                }
              ]
            }
          ]
        },
        {
          "pve_or_pvp": "PVE",
          "visible_in_info_window": true,
          "chance_percent": 100.0,
          "requires": [
            "(source>kMeter > 0) && (target>enttype == critter)"
          ],
          "effects": [
            {
              "attributes": [
                "Lethal_Dmg"
              ],
              "applies_to": "AbsoluteValue",
              "application_type": "Immediate",
              "target_type": "Affected",
              "magnitude": 1.0,
              "duration": "Instant",
              "flags": [
                "ResistMagnitude",
                "CombatModMagnitude"
              ],
              "stacking": {
                "behavior": "Stack",
                "by_caster": true
              },
              "scaled": [
                {
                  "archetype": "Arachnos Widow",
                  "damage": 33.81,
                  "average": 33.81,
                  "per_activation": 40.73,
                  "per_cast_cycle": 2.64,
                  "display_info": [
                    "33.81 lethal damage on target",
                    "Only if hidden or target placated"
                  ],
                  "base_value": -55.6102,
                  "scale": 0.608
                }
              ]
            }
          ]
        },
        {
          "pve_or_pvp": "PVP",
          "visible_in_info_window": true,
          "chance_percent": 100.0,
          "requires": [
            "target>enttype == player"
          ],
          "effects": [
            {
              "attributes": [
                "Lethal_Dmg"
              ],
              "applies_to": "AbsoluteValue",
              "application_type": "Immediate",
              "target_type": "Affected",
              "magnitude": 1.0,
              "duration": "Instant",
              "flags": [
                "ResistMagnitude",
                "CombatModMagnitude"
              ],
              "stacking": {
                "behavior": "Stack",
                "by_caster": true
              },
              "scaled": [
                {
                  "archetype": "Arachnos Widow",
                  "damage": 82.42,
                  "average": 82.42,
                  "per_activation": 99.3,
                  "per_cast_cycle": 6.42,
                  "display_info": [
                    "82.42 lethal damage on target"
                  ],
                  "base_value": -56.4121,
                  "scale": 1.461
                }
              ]
            }
          ]
        },
        {
          "pve_or_pvp": "PVP",
          "visible_in_info_window": true,
          "chance_percent": 100.0,
          "requires": [
            "(source>kMeter > 0) && (target>enttype == player)"
          ],
          "effects": [
            {
              "attributes": [
                "Lethal_Dmg"
              ],
              "applies_to": "AbsoluteValue",
              "application_type": "Immediate",
              "target_type": "Affected",
              "magnitude": 1.0,
              "duration": "Instant",
              "flags": [
                "ResistMagnitude",
                "CombatModMagnitude"
              ],
              "stacking": {
                "behavior": "Stack",
                "by_caster": true
              },
              "scaled": [
                {
                  "archetype": "Arachnos Widow",
                  "damage": 54.97,
                  "average": 54.97,
                  "per_activation": 66.23,
                  "per_cast_cycle": 4.28,
                  "display_info": [
                    "54.97 lethal damage on target",
                    "Only if hidden or target placated"
                  ],
                  "base_value": -56.4121,
                  "scale": 0.9745
                }
              ]
            }
          ]
        },
        {
          "visible_in_info_window": true,
          "chance_percent": 100.0,
          "effects": [
            {
              "attributes": [
                "ToHit"
              ],
              "applies_to": "CurrentValue",
              "application_type": "OnTick",
              "tick_chance_percent": 100.0,
              "target_type": "Self",
              "magnitude": 1.0,
              "duration": "InSeconds",
              "duration_seconds": 10.0,
              "after_delay_seconds": 0.2,
              "flags": [
                "IgnoreResistance",
                "IgnoreLevelDifference"
              ],
              "stacking": {
                "behavior": "Stack",
                "by_caster": true
              },
              "scaled": [
                {
                  "archetype": "Arachnos Widow",
                  "percent": 10.0,
                  "display_info": [
                    "10.00% to hit for 10s on self after 0.2s delay",
                    "Unresistable"
                  ],
                  "base_value": 0.1,
                  "scale": 1.0
                }
              ]
            },
            {
              "attributes": [
                "Smashing_Dmg",
                "Lethal_Dmg",
                "Fire_Dmg",
                "Cold_Dmg",
                "Energy_Dmg",
                "Negative_Energy_Dmg",
                "Psionic_Dmg",
                "Toxic_Dmg"
              ],
              "applies_to": "Strength",
              "application_type": "OnTick",
              "tick_chance_percent": 100.0,
              "target_type": "Self",
              "magnitude": 1.0,
              "duration": "InSeconds",
              "duration_seconds": 10.0,
              "after_delay_seconds": 0.2,
              "flags": [
                "IgnoreStrength",
                "IgnoreResistance",
                "IgnoreLevelDifference"
              ],
              "stacking": {
                "behavior": "Stack",
                "by_caster": true
              },
              "scaled": [
                {
                  "archetype": "Arachnos Widow",
                  "percent": 30.0,
                  "display_info": [
                    "30.00% strength to smashing damage, lethal damage, fire damage, cold damage, energy damage, negative energy damage, psionic damage, toxic damage for 10s on self after 0.2s delay",
                    "Ignores buffs and enhancements",
                    "Unresistable"
                  ],
                  "base_value": 0.1,
                  "scale": 3.0
                }
              ]
            }
          ]
        }
      ]
    },
    {
      "name": "Widow_Training.Widow_Training.Spin",
      "display_name": "Spin",
      "icon": "https://reborn-team.github.io/PowersAPI/assets/powers/dd/widowtraining_spin.png",
      "display_help": "Spin does moderate lethal damage to all foes within an 8' radius of you, then poisons them. The poison does toxic damage over time and slows their recovery rate and movement speed. NOTE: This power may deal critical damage if used after a successful Placate or while the user is hidden with the Night Widow or Fortunata Mask Presence power. Damage: Moderate, Recharge: Slow",
      "display_short_help": "PBAoE Melee, Moderate DMG(Lethal), DoT(Toxic), -Recharge, -SPD",
      "display_info": {
        "Endurance Cost": "15.44",
        "Power Type": "Click",
        "Effect Area": "AoE — 8 ft. radius (10 targets max)",
        "Attack Types": "Melee, Lethal",
        "Recharge Time": "14s",
        "Available Level": "12",
        "Activation Time": "2.5s",
        "Target Type": "Self"
      },
      "attack_types": [
        "Melee_Def",
        "Lethal_Def"
      ],
      "enhancements_allowed": [
        "Reduce Endurance Cost",
        "Enhance Recharge Speed",
        "Enhance Damage",
        "Enhance Accuracy"
      ],
      "enhancement_set_categories_allowed": [
        "Soldiers of Arachnos Archetype Sets",
        "Universal Damage Sets",
        "PBAoE Damage"
      ],
      "available_at_level": 12,
      "auto_issue": false,
      "power_type": "Click",
      "accuracy": 1.0,
      "effect_area": {
        "area": "AoE",
        "max_targets_hit": 10,
        "radius_feet": 8.0
      },
      "target_type_tags": [
        "Self",
        "Alive",
        "Dead"
      ],
      "display_target_type": "Self",
      "requires_line_of_sight": true,
      "modes_disallowed": [
        "Disable_All"
      ],
      "activate": {
        "cast_time": 2.5,
        "animation_time": 2.5,
        "animation_time_before_hit": 1.2,
        "recharge_time": 14.0,
        "endurance_cost": 15.44
      },
      "effect_groups": [
        {
          "pve_or_pvp": "PVE",
          "visible_in_info_window": true,
          "chance_percent": 100.0,
          "requires": [
            "target>enttype == critter"
          ],
          "effects": [
            {
              "attributes": [
                "Lethal_Dmg"
              ],
              "applies_to": "AbsoluteValue",
              "application_type": "Immediate",
              "target_type": "Affected",
              "magnitude": 1.0,
              "duration": "Instant",
              "flags": [
                "ResistMagnitude",
                "CombatModMagnitude"
              ],
              "stacking": {
                "behavior": "Stack",
                "by_caster": true
              },
              "scaled": [
                {
                  "archetype": "Arachnos Widow",
                  "damage": 73.44,
                  "average": 73.44,
                  "per_activation": 29.38,
                  "per_cast_cycle": 4.45,
                  "display_info": [
                    "73.44 lethal damage on target"
                  ],
                  "base_value": -55.6102,
                  "scale": 1.3206
                }
              ]
            }
          ]
        },
        {
          "pve_or_pvp": "PVE",
          "visible_in_info_window": true,
          "chance_percent": 50.0,
          "requires": [
            "(source>kMeter > 0) && (target>enttype == critter)"
          ],
          "effects": [
            {
              "attributes": [
                "Lethal_Dmg"
              ],
              "applies_to": "AbsoluteValue",
              "application_type": "Immediate",
              "target_type": "Affected",
              "magnitude": 1.0,
              "duration": "Instant",
              "flags": [
                "ResistMagnitude",
                "CombatModMagnitude"
              ],
              "stacking": {
                "behavior": "Stack",
                "by_caster": true
              },
              "scaled": [
                {
                  "archetype": "Arachnos Widow",
                  "damage": 48.96,
                  "average": 24.48,
                  "per_activation": 9.79,
                  "per_cast_cycle": 1.48,
                  "display_info": [
                    "50.00% chance for 48.96 lethal damage on target",
                    "Only if hidden or target placated"
                  ],
                  "base_value": -55.6102,
                  "scale": 0.8804
                }
              ]
            }
          ]
        },
        {
          "pve_or_pvp": "PVP",
          "visible_in_info_window": true,
          "chance_percent": 100.0,
          "requires": [
            "target>enttype == player"
          ],
          "effects": [
            {
              "attributes": [
                "Lethal_Dmg"
              ],
              "applies_to": "AbsoluteValue",
              "application_type": "Immediate",
              "target_type": "Affected",
              "magnitude": 1.0,
              "duration": "Instant",
              "flags": [
                "ResistMagnitude",
                "CombatModMagnitude"
              ],
              "stacking": {
                "behavior": "Stack",
                "by_caster": true
              },
              "scaled": [
                {
                  "archetype": "Arachnos Widow",
                  "damage": 87.35,
                  "average": 87.35,
                  "per_activation": 34.94,
                  "per_cast_cycle": 5.29,
                  "display_info": [
                    "87.35 lethal damage on target"
                  ],
                  "base_value": -56.4121,
                  "scale": 1.5485
                }
              ]
            }
          ]
        },
        {
          "pve_or_pvp": "PVP",
          "visible_in_info_window": true,
          "chance_percent": 50.0,
          "requires": [
            "(source>kMeter > 0) && (target>enttype == player)"
          ],
          "effects": [
            {
              "attributes": [
                "Lethal_Dmg"
              ],
              "applies_to": "AbsoluteValue",
              "application_type": "Immediate",
              "target_type": "Affected",
              "magnitude": 1.0,
              "duration": "Instant",
              "flags": [
                "ResistMagnitude",
                "CombatModMagnitude"
              ],
              "stacking": {
                "behavior": "Stack",
                "by_caster": true
              },
              "scaled": [
                {
                  "archetype": "Arachnos Widow",
                  "damage": 58.27,
                  "average": 29.14,
                  "per_activation": 11.66,
                  "per_cast_cycle": 1.77,
                  "display_info": [
                    "50.00% chance for 58.27 lethal damage on target",
                    "Only if hidden or target placated"
                  ],
                  "base_value": -56.4121,
                  "scale": 1.0329
                }
              ]
            }
          ]
        },
        {
          "visible_in_info_window": true,
          "chance_percent": 100.0,
          "effects": [
            {
              "attributes": [
                "RunningSpeed",
                "FlyingSpeed",
                "JumpingSpeed"
              ],
              "applies_to": "CurrentValue",
              "application_type": "OnTick",
              "tick_chance_percent": 100.0,
              "target_type": "Affected",
              "magnitude": 1.0,
              "duration": "InSeconds",
              "duration_seconds": 6.0,
              "flags": [
                "ResistMagnitude",
                "CombatModMagnitude"
              ],
              "stacking": {
                "behavior": "Stack",
                "by_caster": true
              },
              "scaled": [
                {
                  "archetype": "Arachnos Widow",
                  "percent": -20.0,
                  "display_info": [
                    "-20.00% run speed, fly speed, jump speed for 6s on target"
                  ],
                  "base_value": -1.0,
                  "scale": 0.2
                }
              ]
            },
            {
              "attributes": [
                "JumpHeight",
                "RechargeTime"
              ],
              "applies_to": "Strength",
              "application_type": "OnTick",
              "tick_chance_percent": 100.0,
              "target_type": "Affected",
              "magnitude": 1.0,
              "duration": "InSeconds",
              "duration_seconds": 6.0,
              "flags": [
                "IgnoreStrength",
                "ResistMagnitude",
                "CombatModMagnitude"
              ],
              "stacking": {
                "behavior": "Stack",
                "by_caster": true
              },
              "scaled": [
                {
                  "archetype": "Arachnos Widow",
                  "percent": -20.0,
                  "display_info": [
                    "-20.00% strength to jump height, recharge for 6s on target",
                    "Ignores buffs and enhancements"
                  ],
                  "base_value": -1.0,
                  "scale": 0.2
                }
              ]
            },
            {
              "attributes": [
                "Toxic_Dmg"
              ],
              "applies_to": "AbsoluteValue",
              "application_type": "OnTick",
              "tick_chance_percent": 100.0,
              "target_type": "Affected",
              "magnitude": 1.0,
              "duration": "InSeconds",
              "duration_seconds": 3.1,
              "after_delay_seconds": 0.5,
              "continuous_apply_seconds": 1.0,
              "ticks": 4,
              "flags": [
                "CancelOnMiss",
                "ResistMagnitude",
                "CombatModMagnitude"
              ],
              "stacking": {
                "behavior": "Stack",
                "by_caster": true
              },
              "scaled": [
                {
                  "archetype": "Arachnos Widow",
                  "damage": 5.56,
                  "average": 5.56,
                  "per_activation": 2.22,
                  "per_cast_cycle": 0.34,
                  "display_info": [
                    "4 ticks of 5.56 toxic damage over 3.1s on target after 0.5s delay"
                  ],
                  "base_value": -55.6102,
                  "scale": 0.1
                }
              ]
            }
          ]
        }
      ]
    },
    {
      "name": "Widow_Training.Widow_Training.Strike",
      "display_name": "Lunge",
      "icon": "https://reborn-team.github.io/PowersAPI/assets/powers/f7/widowtraining_lunge.png",
      "display_help": "Lunge does high lethal damage to your foe, then poisons them. The poison does toxic damage over time and slows their recovery rate and movement speed. NOTE: This power will deal critical damage if used after a successful Placate or while the user is hidden with the Night Widow or Fortunata Mask Presence power. Damage: High, Recharge: Slow",
      "display_short_help": "High DMG (Lethal), DoT(Toxic), -Recharge, -SPD",
      "display_info": {
        "Effect Area": "Single Target",
        "Endurance Cost": "9.48",
        "Recharge Time": "12s",
        "Target Type": "Enemies",
        "Attack Types": "Melee, Lethal",
        "Available Level": "12",
        "Power Range": "7 ft.",
        "Activation Time": "0.83s",
        "Power Type": "Click"
      },
      "attack_types": [
        "Melee_Def",
        "Lethal_Def"
      ],
      "enhancements_allowed": [
        "Reduce Endurance Cost",
        "Enhance Recharge Speed",
        "Enhance Damage",
        "Enhance Accuracy"
      ],
      "enhancement_set_categories_allowed": [
        "Melee Damage",
        "Soldiers of Arachnos Archetype Sets",
        "Universal Damage Sets"
      ],
      "available_at_level": 12,
      "auto_issue": false,
      "power_type": "Click",
      "accuracy": 1.0,
      "effect_area": {
        "area": "SingleTarget",
        "range_feet": 7.0
      },
      "target_type_tags": [
        "Foe"
      ],
      "display_target_type": "Enemies",
      "requires_line_of_sight": true,
      "modes_disallowed": [
        "Disable_All"
      ],
      "activate": {
        "cast_time": 0.83,
        "animation_time": 0.83,
        "animation_time_before_hit": 0.53,
        "recharge_time": 12.0,
        "endurance_cost": 9.48
      },
      "effect_groups": [
        {
          "pve_or_pvp": "PVE",
          "visible_in_info_window": true,
          "chance_percent": 100.0,
          "requires": [
            "target>enttype == critter"
          ],
          "effects": [
            {
              "attributes": [
                "Lethal_Dmg"
              ],
              "applies_to": "AbsoluteValue",
              "application_type": "Immediate",
              "target_type": "Affected",
              "magnitude": 1.0,
              "duration": "Instant",
              "flags": [
                "ResistMagnitude",
                "CombatModMagnitude"
              ],
              "stacking": {
                "behavior": "Stack",
                "by_caster": true
              },
              "scaled": [
                {
                  "archetype": "Arachnos Widow",
                  "damage": 101.43,
                  "average": 101.43,
                  "per_activation": 122.2,
                  "per_cast_cycle": 7.91,
                  "display_info": [
                    "101.43 lethal damage on target"
                  ],
                  "base_value": -55.6102,
                  "scale": 1.824
                }
              ]
            }
          ]
        },
        {
          "pve_or_pvp": "PVE",
          "visible_in_info_window": true,
          "chance_percent": 100.0,
          "requires": [
            "(source>kMeter > 0) && (target>enttype == critter)"
          ],
          "effects": [
            {
              "attributes": [
                "Lethal_Dmg"
              ],
              "applies_to": "AbsoluteValue",
              "application_type": "Immediate",
              "target_type": "Affected",
              "magnitude": 1.0,
              "duration": "Instant",
              "flags": [
                "ResistMagnitude",
                "CombatModMagnitude"
              ],
              "stacking": {
                "behavior": "Stack",
                "by_caster": true
              },
              "scaled": [
                {
                  "archetype": "Arachnos Widow",
                  "damage": 67.62,
                  "average": 67.62,
                  "per_activation": 81.47,
                  "per_cast_cycle": 5.27,
                  "display_info": [
                    "67.62 lethal damage on target",
                    "Only if hidden or target placated"
                  ],
                  "base_value": -55.6102,
                  "scale": 1.216
                }
              ]
            }
          ]
        },
        {
          "pve_or_pvp": "PVP",
          "visible_in_info_window": true,
          "chance_percent": 100.0,
          "requires": [
            "target>enttype == player"
          ],
          "effects": [
            {
              "attributes": [
                "Lethal_Dmg"
              ],
              "applies_to": "AbsoluteValue",
              "application_type": "Immediate",
              "target_type": "Affected",
              "magnitude": 1.0,
              "duration": "Instant",
              "flags": [
                "ResistMagnitude",
                "CombatModMagnitude"
              ],
              "stacking": {
                "behavior": "Stack",
                "by_caster": true
              },
              "scaled": [
                {
                  "archetype": "Arachnos Widow",
                  "damage": 82.42,
                  "average": 82.42,
                  "per_activation": 99.3,
                  "per_cast_cycle": 6.42,
                  "display_info": [
                    "82.42 lethal damage on target"
                  ],
                  "base_value": -56.4121,
                  "scale": 1.461
                }
              ]
            }
          ]
        },
        {
          "pve_or_pvp": "PVP",
          "visible_in_info_window": true,
          "chance_percent": 100.0,
          "requires": [
            "(source>kMeter > 0) && (target>enttype == player)"
          ],
          "effects": [
            {
              "attributes": [
                "Lethal_Dmg"
              ],
              "applies_to": "AbsoluteValue",
              "application_type": "Immediate",
              "target_type": "Affected",
              "magnitude": 1.0,
              "duration": "Instant",
              "flags": [
                "ResistMagnitude",
                "CombatModMagnitude"
              ],
              "stacking": {
                "behavior": "Stack",
                "by_caster": true
              },
              "scaled": [
                {
                  "archetype": "Arachnos Widow",
                  "damage": 54.97,
                  "average": 54.97,
                  "per_activation": 66.23,
                  "per_cast_cycle": 4.28,
                  "display_info": [
                    "54.97 lethal damage on target",
                    "Only if hidden or target placated"
                  ],
                  "base_value": -56.4121,
                  "scale": 0.9745
                }
              ]
            }
          ]
        },
        {
          "visible_in_info_window": true,
          "chance_percent": 100.0,
          "effects": [
            {
              "attributes": [
                "RunningSpeed",
                "FlyingSpeed",
                "JumpingSpeed"
              ],
              "applies_to": "CurrentValue",
              "application_type": "OnTick",
              "tick_chance_percent": 100.0,
              "target_type": "Affected",
              "magnitude": 1.0,
              "duration": "InSeconds",
              "duration_seconds": 8.0,
              "flags": [
                "ResistMagnitude",
                "CombatModMagnitude"
              ],
              "stacking": {
                "behavior": "Stack",
                "by_caster": true
              },
              "scaled": [
                {
                  "archetype": "Arachnos Widow",
                  "percent": -30.0,
                  "display_info": [
                    "-30.00% run speed, fly speed, jump speed for 8s on target"
                  ],
                  "base_value": -1.0,
                  "scale": 0.3
                }
              ]
            },
            {
              "attributes": [
                "JumpHeight",
                "RechargeTime"
              ],
              "applies_to": "Strength",
              "application_type": "OnTick",
              "tick_chance_percent": 100.0,
              "target_type": "Affected",
              "magnitude": 1.0,
              "duration": "InSeconds",
              "duration_seconds": 8.0,
              "flags": [
                "IgnoreStrength",
                "ResistMagnitude",
                "CombatModMagnitude"
              ],
              "stacking": {
                "behavior": "Stack",
                "by_caster": true
              },
              "scaled": [
                {
                  "archetype": "Arachnos Widow",
                  "percent": -30.0,
                  "display_info": [
                    "-30.00% strength to jump height, recharge for 8s on target",
                    "Ignores buffs and enhancements"
                  ],
                  "base_value": -1.0,
                  "scale": 0.3
                }
              ]
            },
            {
              "attributes": [
                "Toxic_Dmg"
              ],
              "applies_to": "AbsoluteValue",
              "application_type": "OnTick",
              "tick_chance_percent": 100.0,
              "target_type": "Affected",
              "magnitude": 1.0,
              "duration": "InSeconds",
              "duration_seconds": 3.1,
              "after_delay_seconds": 0.5,
              "continuous_apply_seconds": 1.0,
              "ticks": 4,
              "flags": [
                "CancelOnMiss",
                "ResistMagnitude",
                "CombatModMagnitude"
              ],
              "stacking": {
                "behavior": "Stack",
                "by_caster": true
              },
              "scaled": [
                {
                  "archetype": "Arachnos Widow",
                  "damage": 5.56,
                  "average": 5.56,
                  "per_activation": 6.7,
                  "per_cast_cycle": 0.43,
                  "display_info": [
                    "4 ticks of 5.56 toxic damage over 3.1s on target after 0.5s delay"
                  ],
                  "base_value": -55.6102,
                  "scale": 0.1
                }
              ]
            }
          ]
        }
      ]
    },
    {
      "name": "Widow_Training.Widow_Training.Confront",
      "display_name": "Confront",
      "icon": "https://reborn-team.github.io/PowersAPI/assets/powers/ad/widowtraining_confront.png",
      "display_help": "Challenges a foe to attack you. Useful to pull a villain off an ally who finds himself in over his head. A To Hit check required to Taunt enemy players, but is not needed against critter targets. Recharge: Very Fast",
      "display_short_help": "Ranged, Foe Taunt",
      "display_info": {
        "Power Type": "Click",
        "Attack Types": "Ranged",
        "Effect Area": "Single Target",
        "Activation Time": "1.67s",
        "Available Level": "18",
        "Power Range": "80 ft.",
        "Target Type": "Enemies",
        "Recharge Time": "3s"
      },
      "attack_types": [
        "Ranged_Def"
      ],
      "enhancements_allowed": [
        "Enhance Taunt",
        "Enhance Range",
        "Enhance Recharge Speed",
        "Enhance Accuracy"
      ],
      "enhancement_set_categories_allowed": [
        "Taunt"
      ],
      "available_at_level": 18,
      "auto_issue": false,
      "power_type": "Click",
      "accuracy": 1.0,
      "effect_area": {
        "area": "SingleTarget",
        "range_feet": 80.0
      },
      "target_type_tags": [
        "Foe"
      ],
      "display_target_type": "Enemies",
      "target_auto_hit_tags": [
        [
          "Foe"
        ]
      ],
      "display_target_auto_hit": [
        "Enemies"
      ],
      "requires_line_of_sight": true,
      "modes_disallowed": [
        "Disable_All"
      ],
      "activate": {
        "cast_time": 1.67,
        "animation_time": 1.67,
        "animation_time_before_hit": 0.67,
        "recharge_time": 3.0,
        "endurance_cost": 0.0
      },
      "effect_groups": [
        {
          "pve_or_pvp": "PVE",
          "visible_in_info_window": true,
          "chance_percent": 100.0,
          "requires": [
            "target>enttype == critter"
          ],
          "effects": [
            {
              "attributes": [
                "Taunt"
              ],
              "applies_to": "AbsoluteValue",
              "application_type": "OnTick",
              "target_type": "Affected",
              "magnitude": 4.0,
              "duration": "InSecondsScaled",
              "flags": [
                "ResistDuration",
                "CombatModDuration"
              ],
              "stacking": {
                "behavior": "Stack",
                "by_caster": true
              },
              "scaled": [
                {
                  "archetype": "Arachnos Widow",
                  "duration_seconds": 26.25,
                  "display_info": [
                    "4.0 taunt for 26.25s on target"
                  ],
                  "base_value": 1.75,
                  "scale": 15.0
                }
              ]
            }
          ]
        },
        {
          "pve_or_pvp": "PVP",
          "visible_in_info_window": true,
          "chance_percent": 100.0,
          "requires": [
            "(target>enttype == player) && ((@ToHitRoll < @ToHit) || @ForceHit)"
          ],
          "effects": [
            {
              "attributes": [
                "Taunt"
              ],
              "applies_to": "AbsoluteValue",
              "application_type": "OnTick",
              "target_type": "Affected",
              "magnitude": 4.0,
              "duration": "InSecondsScaled",
              "flags": [
                "ResistDuration",
                "CombatModDuration"
              ],
              "stacking": {
                "behavior": "Stack",
                "by_caster": true
              },
              "scaled": [
                {
                  "archetype": "Arachnos Widow",
                  "duration_seconds": 7.0,
                  "display_info": [
                    "4.0 taunt for 7s on target"
                  ],
                  "base_value": 1.75,
                  "scale": 4.0
                }
              ]
            }
          ]
        }
      ]
    }
  ]
}